{
	"name": "walkstartLback_biped",
	"frames": [
		[
			{
				"ang": "{0 -90.0001 0}",
				"pos": "[0 0 0]"
			},
			{
				"ang": "{-1.0704 2.118 86.7935}",
				"pos": "[-4.9922 -47.6001 134.5821]"
			},
			{
				"ang": "{-2.2086 -2.0356 -23.5937}",
				"pos": "[0 27.0678 0]"
			},
			{
				"ang": "{-5.2006 -4.6329 -40.8405}",
				"pos": "[0.001 85.0156 0]"
			},
			{
				"ang": "{-6.2515 -176.6249 -163.7738}",
				"pos": "[-0.001 80.8477 18.2991]"
			},
			{
				"ang": "{-3.2908 -2.1001 15.5132}",
				"pos": "[-0.001 48.6118 -0.0002]"
			},
			{
				"ang": "{0.2204 0.0109 5.4049}",
				"pos": "[0 32.1211 0.0001]"
			},
			{
				"ang": "{1.7828 -175.304 9.419}",
				"pos": "[-19.127 15.8926 14.8353]"
			},
			{
				"ang": "{-2.0367 176.0418 -170.5607}",
				"pos": "[19.1289 15.8931 14.8358]"
			},
			{
				"ang": "{37.7701 -150.3463 -89.4573}",
				"pos": "[56.7178 51.3677 45.5896]"
			},
			{
				"ang": "{20.3992 -7.2069 78.6905}",
				"pos": "[0 54.1127 -0.001]"
			},
			{
				"ang": "{0 0 -83.9477}",
				"pos": "[0 75.4199 0]"
			},
			{
				"ang": "{40.5551 7.344 50.8868}",
				"pos": "[0 89.4588 0]"
			},
			{
				"ang": "{-41.514 150.9892 -92.3529}",
				"pos": "[-56.1875 46.2505 32.6714]"
			},
			{
				"ang": "{-16.4432 19.2353 75.9711}",
				"pos": "[0.0005 54.1113 0.0002]"
			},
			{
				"ang": "{0 0 -81.6114}",
				"pos": "[0.001 75.4199 0.0005]"
			},
			{
				"ang": "{-60.2405 -8.0643 40.0651}",
				"pos": "[0 89.459 0]"
			},
			{
				"ang": "{22.0704 -159.5691 -49.2655}",
				"pos": "[52.248 0.0017 0.001]"
			},
			{
				"ang": "{0 0 64.3311}",
				"pos": "[0.001 80.4251 0]"
			},
			{
				"ang": "{0.6903 -22.3254 -80.3429}",
				"pos": "[0 78.0723 0.0002]"
			},
			{
				"ang": "{-4.5387 151.9979 -42.4346}",
				"pos": "[-52.6133 0.0036 -0.0137]"
			},
			{
				"ang": "{0 0 72.3949}",
				"pos": "[-0.0005 80.4258 -0.0002]"
			},
			{
				"ang": "{-6.9859 35.6122 -98.9904}",
				"pos": "[0 78.0721 0]"
			},
			{
				"ang": "{0.6611 1.0359 -22.2461}",
				"pos": "[-15.4541 200 91.9375]"
			}
		],
		[
			{
				"ang": "{0 -89.4202 0}",
				"pos": "[-0.2437 0 0]"
			},
			{
				"ang": "{-0.9251 1.3739 87.4759}",
				"pos": "[-3.4619 -45.6411 133.3452]"
			},
			{
				"ang": "{-2.0698 -2.8012 -24.1656}",
				"pos": "[0.001 27.0678 0]"
			},
			{
				"ang": "{-4.5352 -4.5604 -40.5909}",
				"pos": "[0 85.0154 -0.0005]"
			},
			{
				"ang": "{-5.2701 -178.3446 -163.5152}",
				"pos": "[-0.002 80.8467 18.2988]"
			},
			{
				"ang": "{-4.2216 -3.5456 18.5224}",
				"pos": "[0.001 48.6123 0.0002]"
			},
			{
				"ang": "{0.1063 -0.6335 3.3517}",
				"pos": "[0 32.1211 0.0001]"
			},
			{
				"ang": "{1.6801 -175.5985 9.0492}",
				"pos": "[-19.1279 15.8936 14.8351]"
			},
			{
				"ang": "{-1.9886 176.2879 -170.9276}",
				"pos": "[19.1279 15.8931 14.8359]"
			},
			{
				"ang": "{37.827 -150.3874 -89.9941}",
				"pos": "[56.5518 51.2256 45.5161]"
			},
			{
				"ang": "{19.8943 -11.2032 77.0348}",
				"pos": "[0 54.1127 0]"
			},
			{
				"ang": "{0 0 -83.2298}",
				"pos": "[0.001 75.4194 -0.0002]"
			},
			{
				"ang": "{37.3324 5.0713 44.5749}",
				"pos": "[-0.001 89.4587 0.0005]"
			},
			{
				"ang": "{-41.4597 150.9844 -92.3684}",
				"pos": "[-56.5508 46.1064 32.752]"
			},
			{
				"ang": "{-15.5426 22.8981 74.8559}",
				"pos": "[-0.0005 54.1123 -0.0006]"
			},
			{
				"ang": "{0 0 -80.5377}",
				"pos": "[-0.001 75.4199 0]"
			},
			{
				"ang": "{-59.0687 -5.3143 35.481}",
				"pos": "[0 89.4585 0]"
			},
			{
				"ang": "{22.0551 -159.6674 -49.8453}",
				"pos": "[52.249 0.0017 0.002]"
			},
			{
				"ang": "{0 0 67.5512}",
				"pos": "[-0.001 80.4257 -0.0005]"
			},
			{
				"ang": "{-0.332 -21.7947 -82.2892}",
				"pos": "[0.001 78.0718 -0.0002]"
			},
			{
				"ang": "{-5.4773 151.1231 -41.0529}",
				"pos": "[-52.6123 0.0036 -0.0132]"
			},
			{
				"ang": "{0 0 72.5509}",
				"pos": "[-0.0005 80.4248 0.0002]"
			},
			{
				"ang": "{-5.3392 35.8389 -98.7658}",
				"pos": "[0 78.0714 0]"
			},
			{
				"ang": "{0.6611 1.0359 -22.2461}",
				"pos": "[-15.4531 200 91.9375]"
			}
		],
		[
			{
				"ang": "{0 -88.2988 0.0118}",
				"pos": "[-0.8091 0 0]"
			},
			{
				"ang": "{-0.7819 0.3604 88.3748}",
				"pos": "[-0.5293 -42.7124 132.1035]"
			},
			{
				"ang": "{-2.0404 -4.2278 -24.9717}",
				"pos": "[0 27.0678 -0.0005]"
			},
			{
				"ang": "{-3.6663 -4.5051 -39.922}",
				"pos": "[0 85.0154 0.0005]"
			},
			{
				"ang": "{-3.7439 179.2026 -163.4521}",
				"pos": "[0 80.8467 18.2991]"
			},
			{
				"ang": "{-5.6095 -5.7827 22.9166}",
				"pos": "[-0.001 48.6123 0]"
			},
			{
				"ang": "{-0.2927 -1.6271 0.731}",
				"pos": "[-0.001 32.1211 -0.0001]"
			},
			{
				"ang": "{1.5012 -176.1182 8.4027}",
				"pos": "[-19.1279 15.8926 14.8352]"
			},
			{
				"ang": "{-1.9055 176.7169 -171.5723}",
				"pos": "[19.127 15.8931 14.8358]"
			},
			{
				"ang": "{37.9103 -150.4587 -90.8802}",
				"pos": "[56.3096 51.0381 45.3696]"
			},
			{
				"ang": "{18.6916 -17.5531 73.2093}",
				"pos": "[0.0005 54.1125 0]"
			},
			{
				"ang": "{0 0 -80.419}",
				"pos": "[-0.001 75.4199 -0.0005]"
			},
			{
				"ang": "{32.9876 3.4415 36.279}",
				"pos": "[0 89.4585 0.0005]"
			},
			{
				"ang": "{-41.2923 150.9518 -92.2658}",
				"pos": "[-57.168 45.8896 32.9272]"
			},
			{
				"ang": "{-14.0609 27.9614 73.8627}",
				"pos": "[0 54.1123 0.0002]"
			},
			{
				"ang": "{0 0 -79.1694}",
				"pos": "[0 75.4198 0]"
			},
			{
				"ang": "{-57.2448 -1.3567 28.7202}",
				"pos": "[-0.001 89.4595 -0.0001]"
			},
			{
				"ang": "{22.3114 -160.2817 -50.2537}",
				"pos": "[52.249 0.0017 0.0015]"
			},
			{
				"ang": "{0 0 71.8367}",
				"pos": "[0 80.4255 0.0005]"
			},
			{
				"ang": "{-1.6209 -20.6134 -85.3775}",
				"pos": "[0.001 78.0713 0.0002]"
			},
			{
				"ang": "{-6.7333 149.4995 -38.8183}",
				"pos": "[-52.6133 0.0036 -0.0137]"
			},
			{
				"ang": "{0 0 71.5601}",
				"pos": "[-0.0005 80.4238 -0.0002]"
			},
			{
				"ang": "{-3.1974 36.2082 -97.6183}",
				"pos": "[0 78.0718 -0.001]"
			},
			{
				"ang": "{0.6611 1.0359 -22.2461}",
				"pos": "[-15.4521 200 91.9375]"
			}
		],
		[
			{
				"ang": "{0 -86.5762 0.0057}",
				"pos": "[-1.6909 0 0]"
			},
			{
				"ang": "{-0.7836 -0.5288 89.3569}",
				"pos": "[4.0264 -39.2402 131.1702]"
			},
			{
				"ang": "{-2.3062 -6.1424 -25.9849}",
				"pos": "[0 27.0678 0]"
			},
			{
				"ang": "{-2.8878 -4.394 -38.9016}",
				"pos": "[0.001 85.0156 0.0005]"
			},
			{
				"ang": "{-2.0638 176.7756 -163.9247}",
				"pos": "[0 80.8467 18.2993]"
			},
			{
				"ang": "{-7.0178 -8.2211 27.1076}",
				"pos": "[-0.001 48.6123 0.0002]"
			},
			{
				"ang": "{-1.0037 -2.7012 -1.2647}",
				"pos": "[0 32.1211 0.0001]"
			},
			{
				"ang": "{1.2483 -176.847 7.506}",
				"pos": "[-19.127 15.8931 14.8352]"
			},
			{
				"ang": "{-1.7955 177.3056 -172.4643}",
				"pos": "[19.127 15.8926 14.8358]"
			},
			{
				"ang": "{37.8417 -150.5402 -92.1298}",
				"pos": "[56.0576 50.7847 45.0864]"
			},
			{
				"ang": "{16.5124 -24.563 67.2404}",
				"pos": "[0 54.1127 0]"
			},
			{
				"ang": "{0 0 -74.6115}",
				"pos": "[0.001 75.4199 -0.0005]"
			},
			{
				"ang": "{29.2629 2.2285 27.4066}",
				"pos": "[0 89.4595 0.0005]"
			},
			{
				"ang": "{-40.9267 150.8675 -91.8788}",
				"pos": "[-57.9951 45.5859 33.1523]"
			},
			{
				"ang": "{-12.1755 32.6621 74.4003}",
				"pos": "[0 54.1123 -0.0005]"
			},
			{
				"ang": "{0 0 -79.1773}",
				"pos": "[0.001 75.4198 -0.0005]"
			},
			{
				"ang": "{-55.0986 2.5056 21.6721}",
				"pos": "[0 89.4585 -0.0001]"
			},
			{
				"ang": "{23.2058 -161.619 -49.9449}",
				"pos": "[52.249 0.0017 0.0015]"
			},
			{
				"ang": "{0 0 76.4984}",
				"pos": "[0 80.4248 0]"
			},
			{
				"ang": "{-2.8076 -18.7369 -89.5929}",
				"pos": "[0.001 78.0718 0.0007]"
			},
			{
				"ang": "{-8.2999 147.107 -36.2346}",
				"pos": "[-52.6133 0.0036 -0.0132]"
			},
			{
				"ang": "{0 0 68.8667}",
				"pos": "[0.0005 80.4268 0.0005]"
			},
			{
				"ang": "{-0.8882 35.3977 -94.8213}",
				"pos": "[0.0005 78.0717 0]"
			},
			{
				"ang": "{0.6611 1.0359 -22.2461}",
				"pos": "[-15.4531 200 91.9375]"
			}
		],
		[
			{
				"ang": "{0 -84.346 0.0101}",
				"pos": "[-2.8091 0 0]"
			},
			{
				"ang": "{-1.237 -1.4223 90.2741}",
				"pos": "[10.1279 -36.0225 130.6515]"
			},
			{
				"ang": "{-2.7473 -8.1245 -27.0618}",
				"pos": "[0 27.0679 0]"
			},
			{
				"ang": "{-2.1819 -4.2016 -37.647}",
				"pos": "[0 85.0156 0.0005]"
			},
			{
				"ang": "{-0.7206 174.7724 -165.2876}",
				"pos": "[0 80.8462 18.2993]"
			},
			{
				"ang": "{-7.988 -10.6411 29.9729}",
				"pos": "[0 48.6118 0]"
			},
			{
				"ang": "{-1.7812 -3.7392 -1.6808}",
				"pos": "[0 32.1211 0]"
			},
			{
				"ang": "{0.9376 -177.7079 6.4643}",
				"pos": "[-19.127 15.8926 14.8353]"
			},
			{
				"ang": "{-1.6798 177.9848 -173.5064}",
				"pos": "[19.127 15.8926 14.8358]"
			},
			{
				"ang": "{37.6074 -150.6125 -93.5202}",
				"pos": "[55.8604 50.5273 44.6675]"
			},
			{
				"ang": "{13.8636 -30.7485 60.3578}",
				"pos": "[0 54.1133 0]"
			},
			{
				"ang": "{0 0 -67.064}",
				"pos": "[0.0005 75.4204 0]"
			},
			{
				"ang": "{26.4546 0.0887 19.0345}",
				"pos": "[0.0005 89.4595 0]"
			},
			{
				"ang": "{-40.2801 150.7082 -91.0232}",
				"pos": "[-58.9297 45.2358 33.4204]"
			},
			{
				"ang": "{-10.0918 35.7722 77.9617}",
				"pos": "[0 54.1133 -0.0004]"
			},
			{
				"ang": "{0 0 -83.1195}",
				"pos": "[0 75.4197 0]"
			},
			{
				"ang": "{-52.789 4.4778 17.2133}",
				"pos": "[0 89.4595 -0.0002]"
			},
			{
				"ang": "{24.3771 -164.1198 -48.9303}",
				"pos": "[52.25 0.0017 0.002]"
			},
			{
				"ang": "{0 0 80.5407}",
				"pos": "[0.001 80.4255 0]"
			},
			{
				"ang": "{-3.265 -16.3084 -94.3828}",
				"pos": "[0 78.0715 0]"
			},
			{
				"ang": "{-9.4567 143.5731 -34.0605}",
				"pos": "[-52.6143 0.0036 -0.0137]"
			},
			{
				"ang": "{0 0 65.3442}",
				"pos": "[0 80.4248 0.0005]"
			},
			{
				"ang": "{1.2666 31.6626 -89.7987}",
				"pos": "[0 78.0717 0]"
			},
			{
				"ang": "{0.6611 1.0359 -22.2461}",
				"pos": "[-15.4531 200 91.9375]"
			}
		],
		[
			{
				"ang": "{0 -81.591 0.0049}",
				"pos": "[-4.3525 0 0]"
			},
			{
				"ang": "{-2.0505 -2.3664 91.0679}",
				"pos": "[17.5854 -33.7715 130.9221]"
			},
			{
				"ang": "{-3.2239 -9.7573 -28.0717}",
				"pos": "[0 27.0678 0]"
			},
			{
				"ang": "{-1.5488 -3.9246 -36.216}",
				"pos": "[0.001 85.0156 -0.0005]"
			},
			{
				"ang": "{0.2259 172.9076 -167.6427}",
				"pos": "[0.001 80.8477 18.2988]"
			},
			{
				"ang": "{-8.3603 -13.2898 32.1984}",
				"pos": "[-0.001 48.6123 0]"
			},
			{
				"ang": "{-2.4781 -4.8921 -1.0682}",
				"pos": "[0 32.1206 0.0001]"
			},
			{
				"ang": "{0.5804 -178.6412 5.3643}",
				"pos": "[-19.1274 15.8936 14.8348]"
			},
			{
				"ang": "{-1.5832 178.6939 -174.6107}",
				"pos": "[19.1265 15.8936 14.8356]"
			},
			{
				"ang": "{37.1812 -150.6486 -94.8705}",
				"pos": "[55.7852 50.3574 44.1152]"
			},
			{
				"ang": "{11.8335 -35.2361 54.2756}",
				"pos": "[0 54.1128 -0.001]"
			},
			{
				"ang": "{0 0 -60.2019}",
				"pos": "[0.0005 75.4199 0]"
			},
			{
				"ang": "{24.3412 -3.5252 12.3227}",
				"pos": "[-0.001 89.459 0]"
			},
			{
				"ang": "{-39.256 150.4686 -89.4856}",
				"pos": "[-59.8984 44.9277 33.7539]"
			},
			{
				"ang": "{-8.1791 37.7168 82.6157}",
				"pos": "[0 54.1113 0.0001]"
			},
			{
				"ang": "{0 0 -89.2252}",
				"pos": "[0 75.4199 0]"
			},
			{
				"ang": "{-49.56 4.4354 15.7239}",
				"pos": "[-0.001 89.459 -0.0002]"
			},
			{
				"ang": "{25.6493 -167.7372 -47.1243}",
				"pos": "[52.249 0.0017 0.001]"
			},
			{
				"ang": "{0 0 83.159}",
				"pos": "[0 80.4253 -0.0007]"
			},
			{
				"ang": "{-2.5823 -13.6212 -99.2122}",
				"pos": "[0 78.0723 0.0002]"
			},
			{
				"ang": "{-7.4722 139.2216 -34.2069}",
				"pos": "[-52.6143 0.0036 -0.0127]"
			},
			{
				"ang": "{-0 0 63.4913}",
				"pos": "[-0.0005 80.4258 -0.0005]"
			},
			{
				"ang": "{2.5632 28.3865 -81.177}",
				"pos": "[0 78.0716 0.001]"
			},
			{
				"ang": "{0.6611 1.0359 -22.2461}",
				"pos": "[-15.4541 200 91.9375]"
			}
		],
		[
			{
				"ang": "{0 -78.3416 0.0108}",
				"pos": "[-6.126 0 0]"
			},
			{
				"ang": "{-3.1262 -3.4195 91.6706}",
				"pos": "[25.5703 -33.0029 132.1057]"
			},
			{
				"ang": "{-3.5154 -10.6891 -28.8591}",
				"pos": "[-0.001 27.0678 0]"
			},
			{
				"ang": "{-0.934 -3.5828 -34.7286}",
				"pos": "[0 85.0156 0.0005]"
			},
			{
				"ang": "{1.0063 171.2126 -170.1343}",
				"pos": "[-0.001 80.8467 18.2993]"
			},
			{
				"ang": "{-7.7859 -16.0174 33.5135}",
				"pos": "[0.001 48.6123 0]"
			},
			{
				"ang": "{-3.0088 -5.9489 0.2673}",
				"pos": "[-0.001 32.1211 -0.0001]"
			},
			{
				"ang": "{0.1929 -179.5761 4.3046}",
				"pos": "[-19.1274 15.8936 14.8351]"
			},
			{
				"ang": "{-1.5269 179.3754 -175.6826}",
				"pos": "[19.127 15.8945 14.8357]"
			},
			{
				"ang": "{36.5876 -150.6405 -96.1247}",
				"pos": "[55.8613 50.3838 43.4829]"
			},
			{
				"ang": "{10.8165 -37.7602 49.5748}",
				"pos": "[0.001 54.1123 0]"
			},
			{
				"ang": "{-0 0 -53.8332}",
				"pos": "[0.0005 75.4199 0.001]"
			},
			{
				"ang": "{23.0051 -9.08 6.4725}",
				"pos": "[0.0005 89.4595 0]"
			},
			{
				"ang": "{-38.0024 150.2182 -87.5198}",
				"pos": "[-60.8369 44.7627 34.1768]"
			},
			{
				"ang": "{-6.4637 37.873 87.738}",
				"pos": "[-0.0005 54.1123 -0.0004]"
			},
			{
				"ang": "{-0 0 -95.9798}",
				"pos": "[-0.001 75.4197 0.0005]"
			},
			{
				"ang": "{-46.6627 3.5417 16.1237}",
				"pos": "[0.001 89.4595 0.0001]"
			},
			{
				"ang": "{26.5911 -171.9398 -44.5553}",
				"pos": "[52.2495 0.0017 0.002]"
			},
			{
				"ang": "{-0 0 83.7174}",
				"pos": "[-0.001 80.4258 0]"
			},
			{
				"ang": "{-1.1533 -11.1169 -103.3223}",
				"pos": "[0.001 78.072 0.0002]"
			},
			{
				"ang": "{-3.8326 135.704 -37.8644}",
				"pos": "[-52.6133 0.0036 -0.0127]"
			},
			{
				"ang": "{0 0 67.2643}",
				"pos": "[-0.0005 80.4258 0.0002]"
			},
			{
				"ang": "{3.6502 26.9079 -71.6721}",
				"pos": "[0.0005 78.0721 0]"
			},
			{
				"ang": "{0.6611 1.0359 -22.2461}",
				"pos": "[-15.4526 200 91.9375]"
			}
		],
		[
			{
				"ang": "{0 -74.5912 0.0127}",
				"pos": "[-8.3276 0 0]"
			},
			{
				"ang": "{-4.2679 -4.67 91.96}",
				"pos": "[33.8369 -34.373 134.2222]"
			},
			{
				"ang": "{-3.4347 -10.6833 -29.2701}",
				"pos": "[0 27.0678 0]"
			},
			{
				"ang": "{-0.2824 -3.1694 -33.2362}",
				"pos": "[0 85.0154 0]"
			},
			{
				"ang": "{1.8413 169.8972 -171.9524}",
				"pos": "[-0.001 80.8467 18.2993]"
			},
			{
				"ang": "{-6.1383 -18.4053 33.6896}",
				"pos": "[0.001 48.6113 0.0005]"
			},
			{
				"ang": "{-3.4903 -6.6155 1.9733}",
				"pos": "[0.001 32.1211 0]"
			},
			{
				"ang": "{-0.2102 179.52 3.3306}",
				"pos": "[-19.1279 15.8936 14.835]"
			},
			{
				"ang": "{-1.51 179.9953 -176.6755}",
				"pos": "[19.127 15.8945 14.8359]"
			},
			{
				"ang": "{35.8647 -150.5923 -97.3446}",
				"pos": "[56.1006 50.709 42.7769]"
			},
			{
				"ang": "{10.6419 -39.6088 45.8044}",
				"pos": "[0.0005 54.1128 0]"
			},
			{
				"ang": "{0 0 -47.4082}",
				"pos": "[0 75.42 0]"
			},
			{
				"ang": "{21.9846 -15.3265 0.6078}",
				"pos": "[0 89.4595 -0.001]"
			},
			{
				"ang": "{-36.6715 150.0109 -85.4009}",
				"pos": "[-61.7275 44.8477 34.6953]"
			},
			{
				"ang": "{-4.8565 35.7924 93.5488}",
				"pos": "[-0.0005 54.1123 0]"
			},
			{
				"ang": "{0 0 -102.7148}",
				"pos": "[0 75.4199 0]"
			},
			{
				"ang": "{-45.1885 2.9979 16.3165}",
				"pos": "[-0.001 89.459 0.001]"
			},
			{
				"ang": "{26.9026 -176.5804 -41.8589}",
				"pos": "[52.2495 0.0017 0.002]"
			},
			{
				"ang": "{0 0 82.3429}",
				"pos": "[0 80.4255 -0.0005]"
			},
			{
				"ang": "{0.8431 -8.7592 -106.2731}",
				"pos": "[-0.001 78.0718 -0.0002]"
			},
			{
				"ang": "{-0.6964 132.214 -44.0224}",
				"pos": "[-52.6128 0.0036 -0.0127]"
			},
			{
				"ang": "{0 0 75.9873}",
				"pos": "[-0.0005 80.4268 0.0005]"
			},
			{
				"ang": "{5.5495 27.6548 -63.3372}",
				"pos": "[0 78.0723 0]"
			},
			{
				"ang": "{0.6611 1.0359 -22.2461}",
				"pos": "[-15.4531 200 91.9375]"
			}
		],
		[
			{
				"ang": "{0 -70.4746 0.0145}",
				"pos": "[-10.7681 0 0]"
			},
			{
				"ang": "{-4.4974 -6.0592 91.7329}",
				"pos": "[41.7915 -38.7148 137.0158]"
			},
			{
				"ang": "{-2.9101 -9.7758 -29.106}",
				"pos": "[0.0005 27.0679 -0.001]"
			},
			{
				"ang": "{0.3982 -2.7217 -31.9057}",
				"pos": "[-0.001 85.0156 -0.001]"
			},
			{
				"ang": "{2.4051 171.1074 -172.304}",
				"pos": "[0.0005 80.8462 18.2993]"
			},
			{
				"ang": "{-4.2539 -18.1758 32.5984}",
				"pos": "[-0.001 48.6123 -0.0005]"
			},
			{
				"ang": "{-4.1191 -6.4683 3.7562}",
				"pos": "[0 32.1221 0]"
			},
			{
				"ang": "{-0.5705 178.7977 2.6142}",
				"pos": "[-19.127 15.8926 14.8354]"
			},
			{
				"ang": "{-1.5476 -179.5346 -177.4175}",
				"pos": "[19.1279 15.8926 14.8357]"
			},
			{
				"ang": "{35.0837 -150.5089 -98.4342}",
				"pos": "[56.478 51.3931 42.0229]"
			},
			{
				"ang": "{11.2386 -41.5232 43.69}",
				"pos": "[-0.0005 54.1123 0]"
			},
			{
				"ang": "{-0 0 -43.3304}",
				"pos": "[0.0005 75.42 0]"
			},
			{
				"ang": "{20.7421 -19.1094 -3.0317}",
				"pos": "[-0.0002 89.459 0]"
			},
			{
				"ang": "{-35.501 149.8763 -83.5086}",
				"pos": "[-62.502 45.269 35.2612]"
			},
			{
				"ang": "{-4.3816 32.3947 98.4082}",
				"pos": "[-0.0005 54.1123 0.0002]"
			},
			{
				"ang": "{0 0 -106.9383}",
				"pos": "[-0.001 75.4194 0]"
			},
			{
				"ang": "{-44.2982 4.5837 13.7039}",
				"pos": "[0.001 89.459 0]"
			},
			{
				"ang": "{26.5387 179.1943 -40.4243}",
				"pos": "[52.2495 0.0018 0.001]"
			},
			{
				"ang": "{0 0 80.0805}",
				"pos": "[-0.001 80.4248 0]"
			},
			{
				"ang": "{3.3143 -6.3931 -107.7943}",
				"pos": "[0.001 78.072 -0.0005]"
			},
			{
				"ang": "{0.2645 131.1777 -47.9355}",
				"pos": "[-52.6128 0.0037 -0.0137]"
			},
			{
				"ang": "{0 0 82.2545}",
				"pos": "[0 80.4268 0]"
			},
			{
				"ang": "{6.967 28.2915 -58.2696}",
				"pos": "[-0.0005 78.0716 0]"
			},
			{
				"ang": "{0.6611 1.0359 -22.2461}",
				"pos": "[-15.4531 200 91.9375]"
			}
		],
		[
			{
				"ang": "{0 -65.9821 0.0123}",
				"pos": "[-13.5698 0 0]"
			},
			{
				"ang": "{-4.4619 -7.3911 91.287}",
				"pos": "[48.8271 -45.626 140.6063]"
			},
			{
				"ang": "{-2.1692 -8.8689 -28.6243}",
				"pos": "[0.001 27.0678 -0.001]"
			},
			{
				"ang": "{1.2702 -2.3253 -30.8026}",
				"pos": "[0 85.0156 -0.001]"
			},
			{
				"ang": "{2.7815 173.2667 -172.3334}",
				"pos": "[0 80.8472 18.2993]"
			},
			{
				"ang": "{-2.7499 -16.6021 31.8471}",
				"pos": "[0.0005 48.6113 0]"
			},
			{
				"ang": "{-4.9065 -6.0419 5.3365}",
				"pos": "[-0.0005 32.1211 -0.0001]"
			},
			{
				"ang": "{-0.8772 178.2867 2.1911}",
				"pos": "[-19.1274 15.8926 14.835]"
			},
			{
				"ang": "{-1.6425 -179.2474 -177.8653}",
				"pos": "[19.1265 15.8936 14.8359]"
			},
			{
				"ang": "{34.2585 -150.4024 -99.4306}",
				"pos": "[56.8608 52.2847 41.1646]"
			},
			{
				"ang": "{11.9906 -43.1212 43.3477}",
				"pos": "[0 54.1118 0]"
			},
			{
				"ang": "{0 0 -41.9412}",
				"pos": "[-0.0002 75.4198 0.001]"
			},
			{
				"ang": "{19.6763 -20.2155 -4.2925}",
				"pos": "[0 89.4595 0]"
			},
			{
				"ang": "{-34.5657 149.8044 -81.984}",
				"pos": "[-63.2749 45.8711 35.79]"
			},
			{
				"ang": "{-4.4652 28.9167 101.2065}",
				"pos": "[-0.0005 54.1123 0]"
			},
			{
				"ang": "{0 0 -108.2865}",
				"pos": "[0.001 75.4199 -0.0005]"
			},
			{
				"ang": "{-43.6085 7.3933 9.8}",
				"pos": "[-0.002 89.459 0]"
			},
			{
				"ang": "{26.0762 175.2025 -39.2704}",
				"pos": "[52.249 0.0017 0.001]"
			},
			{
				"ang": "{0 0 76.3238}",
				"pos": "[0 80.4253 -0.0005]"
			},
			{
				"ang": "{5.8248 -3.8586 -107.6241}",
				"pos": "[0 78.072 -0.0005]"
			},
			{
				"ang": "{-0.4956 132.6237 -48.8463}",
				"pos": "[-52.6133 0.0036 -0.0146]"
			},
			{
				"ang": "{0 0 85.0681}",
				"pos": "[0 80.4258 0]"
			},
			{
				"ang": "{7.0913 27.5325 -56.0432}",
				"pos": "[0 78.0719 0]"
			},
			{
				"ang": "{0.6611 1.0359 -22.2461}",
				"pos": "[-15.4526 200.001 91.9375]"
			}
		],
		[
			{
				"ang": "{0 -61.1513 0}",
				"pos": "[-16.5815 0 0]"
			},
			{
				"ang": "{-4.3019 -8.6571 90.7604}",
				"pos": "[54.5479 -54.6465 145.0481]"
			},
			{
				"ang": "{-1.1234 -8.1111 -28.0432}",
				"pos": "[0.0005 27.0678 0.001]"
			},
			{
				"ang": "{2.5542 -2.0821 -29.9928}",
				"pos": "[0 85.0156 0]"
			},
			{
				"ang": "{3.0905 175.8524 -172.3347}",
				"pos": "[0.0005 80.8462 18.2998]"
			},
			{
				"ang": "{-1.7464 -14.1972 32.0679}",
				"pos": "[0.0005 48.6118 -0.0005]"
			},
			{
				"ang": "{-5.9155 -5.1469 6.3431}",
				"pos": "[-0.0005 32.1221 -0.0001]"
			},
			{
				"ang": "{-1.1137 178.0258 2.1079}",
				"pos": "[-19.1274 15.8936 14.8352]"
			},
			{
				"ang": "{-1.7973 -179.1857 -177.9632}",
				"pos": "[19.1272 15.8936 14.8359]"
			},
			{
				"ang": "{33.4049 -150.2699 -100.3457}",
				"pos": "[57.2202 53.2788 40.2109]"
			},
			{
				"ang": "{12.3702 -44.0607 45.0215}",
				"pos": "[-0.0005 54.1128 0.001]"
			},
			{
				"ang": "{-0 0 -43.4335}",
				"pos": "[0.0003 75.4197 0]"
			},
			{
				"ang": "{19.4477 -18.972 -3.9673}",
				"pos": "[-0.0004 89.46 0]"
			},
			{
				"ang": "{-33.7927 149.7666 -80.7}",
				"pos": "[-64.0532 46.5498 36.2622]"
			},
			{
				"ang": "{-4.4606 26.3169 100.5489}",
				"pos": "[-0.0002 54.1123 0.0005]"
			},
			{
				"ang": "{0 0 -107.1558}",
				"pos": "[0.0005 75.4199 0]"
			},
			{
				"ang": "{-43.0744 9.7053 7.1496}",
				"pos": "[0 89.46 0]"
			},
			{
				"ang": "{25.6303 171.5497 -38.0118}",
				"pos": "[52.2495 0.0017 0.002]"
			},
			{
				"ang": "{0 0 70.8932}",
				"pos": "[0 80.4253 0.0005]"
			},
			{
				"ang": "{8.1267 -1.1227 -105.6896}",
				"pos": "[0 78.0715 0]"
			},
			{
				"ang": "{-2.8273 135.3464 -47.627}",
				"pos": "[-52.6118 0.0036 -0.0127]"
			},
			{
				"ang": "{0 0 85.5901}",
				"pos": "[0 80.4248 0]"
			},
			{
				"ang": "{6.4831 26.4036 -55.989}",
				"pos": "[0 78.072 -0.001]"
			},
			{
				"ang": "{0.6611 1.0359 -22.2461}",
				"pos": "[-15.4531 200 91.9375]"
			}
		],
		[
			{
				"ang": "{0 -55.9803 0}",
				"pos": "[-20.6626 0 0]"
			},
			{
				"ang": "{-4.2612 -10.0537 90.3114}",
				"pos": "[58.4263 -65.0781 149.7151]"
			},
			{
				"ang": "{-0.0571 -7.3691 -27.6575}",
				"pos": "[-0.001 27.0678 0.001]"
			},
			{
				"ang": "{3.8622 -1.8718 -29.4195}",
				"pos": "[0.0005 85.0156 0]"
			},
			{
				"ang": "{3.4536 178.9399 -172.3922}",
				"pos": "[0 80.8467 18.2988]"
			},
			{
				"ang": "{-0.5322 -11.795 33.733}",
				"pos": "[0.0005 48.6113 -0.0005]"
			},
			{
				"ang": "{-7.0881 -3.26 6.5541}",
				"pos": "[-0.0002 32.1221 0]"
			},
			{
				"ang": "{-1.2827 177.8991 2.2622}",
				"pos": "[-19.127 15.8936 14.8347]"
			},
			{
				"ang": "{-1.9712 -179.3067 -177.8178}",
				"pos": "[19.1277 15.8936 14.8354]"
			},
			{
				"ang": "{32.5926 -150.132 -101.3954}",
				"pos": "[57.605 54.2383 39.1768]"
			},
			{
				"ang": "{12.3687 -44.7454 47.1387}",
				"pos": "[-0.0002 54.1123 0.001]"
			},
			{
				"ang": "{0 0 -45.4968}",
				"pos": "[0 75.4199 0]"
			},
			{
				"ang": "{20.1277 -16.5107 -3.5311}",
				"pos": "[-0.0005 89.459 0]"
			},
			{
				"ang": "{-33.1676 149.7508 -79.6157}",
				"pos": "[-64.7388 47.1992 36.6641]"
			},
			{
				"ang": "{-4.1795 24.2913 97.6754}",
				"pos": "[0 54.1133 0]"
			},
			{
				"ang": "{0 0 -104.6221}",
				"pos": "[-0.001 75.4204 0]"
			},
			{
				"ang": "{-42.7017 11.3121 6.6138}",
				"pos": "[0.001 89.4595 0]"
			},
			{
				"ang": "{24.7496 168.4378 -36.5225}",
				"pos": "[52.2485 0.0017 0.002]"
			},
			{
				"ang": "{0 0 63.985}",
				"pos": "[0 80.4258 0]"
			},
			{
				"ang": "{10.2328 1.4749 -101.969}",
				"pos": "[0 78.072 0]"
			},
			{
				"ang": "{-6.661 138.3201 -44.2303}",
				"pos": "[-52.6138 0.0037 -0.0127]"
			},
			{
				"ang": "{-0 0 84.2989}",
				"pos": "[0 80.4248 0]"
			},
			{
				"ang": "{5.4796 25.4891 -59.6459}",
				"pos": "[-0.0002 78.0718 0.001]"
			},
			{
				"ang": "{0.6611 1.0359 -22.2461}",
				"pos": "[-15.4531 200 91.9375]"
			}
		],
		[
			{
				"ang": "{0 -50.529 0}",
				"pos": "[-25.5771 0 0]"
			},
			{
				"ang": "{-4.1988 -11.7328 90.1363}",
				"pos": "[60.1968 -75.959 153.2094]"
			},
			{
				"ang": "{1.0483 -6.6941 -27.6216}",
				"pos": "[0.001 27.0678 0]"
			},
			{
				"ang": "{5.2433 -1.7308 -29.0842}",
				"pos": "[0.001 85.0156 -0.001]"
			},
			{
				"ang": "{3.7614 -177.6464 -172.6392}",
				"pos": "[-0.0002 80.8467 18.2993]"
			},
			{
				"ang": "{0.5785 -9.3304 35.5757}",
				"pos": "[0 48.6123 0]"
			},
			{
				"ang": "{-8.1805 -1.0623 6.5162}",
				"pos": "[-0.0002 32.1211 0]"
			},
			{
				"ang": "{-1.4384 177.7821 2.4424}",
				"pos": "[-19.1276 15.8936 14.835]"
			},
			{
				"ang": "{-2.1367 -179.4252 -177.6456}",
				"pos": "[19.1274 15.8936 14.8354]"
			},
			{
				"ang": "{31.8438 -149.9957 -102.7503}",
				"pos": "[58.0049 55.1133 38.0913]"
			},
			{
				"ang": "{11.8627 -45.004 50.8192}",
				"pos": "[-0.0002 54.1123 0]"
			},
			{
				"ang": "{-0 0 -49.614}",
				"pos": "[0.0002 75.4199 0.001]"
			},
			{
				"ang": "{21.8459 -13.0461 -2.512}",
				"pos": "[-0.0002 89.4585 0]"
			},
			{
				"ang": "{-32.6707 149.7466 -78.7191}",
				"pos": "[-65.3257 47.7568 37.0024]"
			},
			{
				"ang": "{-3.9522 22.5804 93.195}",
				"pos": "[0 54.1133 -0.0005]"
			},
			{
				"ang": "{0 0 -100.9191}",
				"pos": "[0 75.4199 0.0005]"
			},
			{
				"ang": "{-41.9606 13.1714 6.8003}",
				"pos": "[0 89.4595 0]"
			},
			{
				"ang": "{23.9216 166.136 -35.4396}",
				"pos": "[52.249 0.0018 0.0029]"
			},
			{
				"ang": "{0 0 57.9359}",
				"pos": "[0 80.4258 0]"
			},
			{
				"ang": "{11.7757 3.8597 -97.9915}",
				"pos": "[0 78.0725 -0.0005]"
			},
			{
				"ang": "{-10.5866 140.698 -39.4175}",
				"pos": "[-52.6128 0.0036 -0.0127]"
			},
			{
				"ang": "{-0 0 82.008}",
				"pos": "[0 80.4248 0]"
			},
			{
				"ang": "{4.8049 25.7889 -66.0407}",
				"pos": "[-0.0005 78.0708 -0.001]"
			},
			{
				"ang": "{0.6611 1.0359 -22.2461}",
				"pos": "[-15.4526 200 91.9375]"
			}
		],
		[
			{
				"ang": "{0 -44.8412 0}",
				"pos": "[-31.2339 0 0]"
			},
			{
				"ang": "{-4.1212 -13.7708 90.2052}",
				"pos": "[59.6821 -86.5195 154.8372]"
			},
			{
				"ang": "{2.2225 -6.0764 -27.8649}",
				"pos": "[0 27.0678 0]"
			},
			{
				"ang": "{6.7296 -1.6384 -29.0153}",
				"pos": "[-0.0002 85.0161 0]"
			},
			{
				"ang": "{3.7339 -173.6937 -173.1928}",
				"pos": "[-0.0005 80.8477 18.2983]"
			},
			{
				"ang": "{1.1955 -6.2764 37.4547}",
				"pos": "[-0.0001 48.6113 0.0005]"
			},
			{
				"ang": "{-9.1406 1.0192 6.563}",
				"pos": "[0.0002 32.1211 0]"
			},
			{
				"ang": "{-1.5831 177.6755 2.6402}",
				"pos": "[-19.1271 15.8926 14.835]"
			},
			{
				"ang": "{-2.2899 -179.5336 -177.453}",
				"pos": "[19.127 15.8916 14.8354]"
			},
			{
				"ang": "{31.1488 -149.8486 -104.3142}",
				"pos": "[58.4102 55.8965 36.9424]"
			},
			{
				"ang": "{11.2528 -44.7759 55.6095}",
				"pos": "[0.0005 54.1123 0.0005]"
			},
			{
				"ang": "{0 0 -55.5003}",
				"pos": "[0.0005 75.4199 0]"
			},
			{
				"ang": "{22.892 -9.3438 -0.2701}",
				"pos": "[-0.0002 89.459 -0.0005]"
			},
			{
				"ang": "{-32.2947 149.7501 -78.0164}",
				"pos": "[-65.832 48.207 37.2549]"
			},
			{
				"ang": "{-3.9405 21.3569 87.5072}",
				"pos": "[0 54.1128 0.001]"
			},
			{
				"ang": "{0 0 -96.4758}",
				"pos": "[0.0005 75.4199 0]"
			},
			{
				"ang": "{-40.7592 14.8139 7.8777}",
				"pos": "[0 89.459 0]"
			},
			{
				"ang": "{23.634 164.5637 -35.3805}",
				"pos": "[52.2488 0.0018 0.0029]"
			},
			{
				"ang": "{0 0 54.2659}",
				"pos": "[0 80.4253 0]"
			},
			{
				"ang": "{12.5706 5.8717 -94.8522}",
				"pos": "[0.0005 78.0719 0]"
			},
			{
				"ang": "{-14.6618 142.2053 -34.1267}",
				"pos": "[-52.6135 0.0036 -0.0117]"
			},
			{
				"ang": "{0 0 79.4549}",
				"pos": "[0.0005 80.4258 0.002]"
			},
			{
				"ang": "{4.7701 27.3792 -73.5448}",
				"pos": "[0.0002 78.0723 -0.001]"
			},
			{
				"ang": "{0.6611 1.0359 -22.2461}",
				"pos": "[-15.4536 200.001 91.9375]"
			}
		],
		[
			{
				"ang": "{0 -38.8983 0.0132}",
				"pos": "[-37.5728 0 0]"
			},
			{
				"ang": "{-4.1532 -16.6552 90.7571}",
				"pos": "[56.5688 -95.3447 154.71]"
			},
			{
				"ang": "{3.5431 -5.4128 -28.4555}",
				"pos": "[0 27.0678 0]"
			},
			{
				"ang": "{8.4245 -1.5673 -29.4311}",
				"pos": "[0 85.0156 -0.001]"
			},
			{
				"ang": "{3.5175 -170.16 -174.1821}",
				"pos": "[-0.0002 80.8457 18.2993]"
			},
			{
				"ang": "{1.4908 -3.1844 38.8549}",
				"pos": "[0.0003 48.6123 0]"
			},
			{
				"ang": "{-9.9024 2.3587 6.9883}",
				"pos": "[0.0002 32.1211 0.0002]"
			},
			{
				"ang": "{-1.7174 177.5983 2.8563}",
				"pos": "[-19.1269 15.8936 14.8352]"
			},
			{
				"ang": "{-2.4361 -179.6128 -177.2443}",
				"pos": "[19.1267 15.8936 14.8359]"
			},
			{
				"ang": "{30.5195 -149.6928 -105.9937}",
				"pos": "[58.8416 56.4629 35.6519]"
			},
			{
				"ang": "{10.9495 -44.4178 59.5875}",
				"pos": "[0.0002 54.1123 -0.0005]"
			},
			{
				"ang": "{0 0 -61.5477}",
				"pos": "[-0.0005 75.4199 0.001]"
			},
			{
				"ang": "{21.961 -5.5771 3.373}",
				"pos": "[0.0005 89.4585 0.0005]"
			},
			{
				"ang": "{-32.0611 149.7542 -77.5592}",
				"pos": "[-66.2244 48.4404 37.3223]"
			},
			{
				"ang": "{-4.3527 21.2771 81.5012}",
				"pos": "[0.0002 54.1133 0]"
			},
			{
				"ang": "{0 0 -91.5739}",
				"pos": "[0 75.4209 0]"
			},
			{
				"ang": "{-38.8111 15.441 9.8387}",
				"pos": "[-0.0005 89.4585 0]"
			},
			{
				"ang": "{23.7135 163.8666 -35.9607}",
				"pos": "[52.2493 0.0017 0.002]"
			},
			{
				"ang": "{0 0 53.3885}",
				"pos": "[0.001 80.4258 -0.0005]"
			},
			{
				"ang": "{12.8628 7.0657 -93.0999}",
				"pos": "[-0.001 78.072 0]"
			},
			{
				"ang": "{-18.8586 142.6647 -28.2735}",
				"pos": "[-52.613 0.0036 -0.0137]"
			},
			{
				"ang": "{0 0 76.7236}",
				"pos": "[-0.0004 80.4253 0]"
			},
			{
				"ang": "{5.1864 29.6635 -81.0874}",
				"pos": "[0.0004 78.0723 -0.001]"
			},
			{
				"ang": "{0.6611 1.0359 -22.2461}",
				"pos": "[-15.4531 199.999 91.9375]"
			}
		],
		[
			{
				"ang": "{0 -32.775 0.0171}",
				"pos": "[-44.4272 0 0]"
			},
			{
				"ang": "{-4.5553 -21.2599 92.808}",
				"pos": "[52.3921 -100.5049 153.5856]"
			},
			{
				"ang": "{5.1999 -4.7635 -29.8433}",
				"pos": "[-0.0002 27.0679 0.001]"
			},
			{
				"ang": "{10.7485 -1.6528 -30.8584}",
				"pos": "[0.0001 85.0156 0.001]"
			},
			{
				"ang": "{4.2953 -169.7552 -175.5336}",
				"pos": "[-0.0003 80.8467 18.2993]"
			},
			{
				"ang": "{3.3169 -2.6851 39.0679}",
				"pos": "[0.0001 48.6123 0]"
			},
			{
				"ang": "{-10.1602 2.9181 7.5891}",
				"pos": "[0.0006 32.1211 -0.0002]"
			},
			{
				"ang": "{-1.8595 177.5975 3.0717}",
				"pos": "[-19.1274 15.8926 14.835]"
			},
			{
				"ang": "{-2.5879 -179.6163 -177.0356}",
				"pos": "[19.1271 15.8936 14.8357]"
			},
			{
				"ang": "{29.94 -149.5337 -107.6796}",
				"pos": "[59.3129 56.4961 33.9907]"
			},
			{
				"ang": "{10.5134 -43.8018 62.639}",
				"pos": "[0.0001 54.1113 0.0005]"
			},
			{
				"ang": "{-0 0 -67.4632}",
				"pos": "[-0.001 75.4199 0]"
			},
			{
				"ang": "{19.7893 -2.5467 7.5411}",
				"pos": "[0.0005 89.459 0]"
			},
			{
				"ang": "{-31.9406 149.7584 -77.3262}",
				"pos": "[-66.5324 48.1357 37.022]"
			},
			{
				"ang": "{-4.9531 21.6277 76.0121}",
				"pos": "[-0.0001 54.1123 -0.001]"
			},
			{
				"ang": "{0 0 -85.6398}",
				"pos": "[0.0002 75.4199 -0.0005]"
			},
			{
				"ang": "{-36.2498 16.4162 10.4323}",
				"pos": "[-0.0001 89.459 0]"
			},
			{
				"ang": "{23.3541 164.2755 -34.7851}",
				"pos": "[52.249 0.0017 0.002]"
			},
			{
				"ang": "{0 0 54.3126}",
				"pos": "[0.001 80.4253 0]"
			},
			{
				"ang": "{12.9682 7.2549 -92.8533}",
				"pos": "[0.0005 78.0721 0]"
			},
			{
				"ang": "{-23.3282 140.9137 -18.7996}",
				"pos": "[-52.6133 0.0037 -0.0127]"
			},
			{
				"ang": "{0 0 72.6734}",
				"pos": "[-0.0005 80.4253 -0.001]"
			},
			{
				"ang": "{6.2965 31.6536 -89.1584}",
				"pos": "[0.0005 78.0718 0]"
			},
			{
				"ang": "{0.6611 1.0359 -22.2461}",
				"pos": "[-15.4536 200 91.9375]"
			}
		],
		[
			{
				"ang": "{0 -26.4991 0}",
				"pos": "[-51.918 0 0]"
			},
			{
				"ang": "{-4.8516 -26.5874 95.9497}",
				"pos": "[47.9021 -101.9541 151.5578]"
			},
			{
				"ang": "{6.7964 -3.845 -31.6624}",
				"pos": "[-0.0002 27.0677 -0.001]"
			},
			{
				"ang": "{12.8309 -1.9646 -33.0278}",
				"pos": "[-0.0002 85.0161 0.001]"
			},
			{
				"ang": "{5.4572 -171.6995 -177.4188}",
				"pos": "[0.0003 80.8477 18.2988]"
			},
			{
				"ang": "{6.5357 -4.3755 38.1721}",
				"pos": "[-0.0004 48.6104 -0.0005]"
			},
			{
				"ang": "{-9.9013 2.9664 8.3694}",
				"pos": "[0 32.1211 0]"
			},
			{
				"ang": "{-2.0017 177.6606 3.2888}",
				"pos": "[-19.1272 15.8936 14.8352]"
			},
			{
				"ang": "{-2.741 -179.5546 -176.8266}",
				"pos": "[19.127 15.8936 14.8357]"
			},
			{
				"ang": "{29.47 -149.3839 -109.2588}",
				"pos": "[59.8974 56.0801 32.1035]"
			},
			{
				"ang": "{10.3926 -43.4629 64.2804}",
				"pos": "[-0.0001 54.1123 0]"
			},
			{
				"ang": "{0 0 -72.3387}",
				"pos": "[0 75.4202 0.001]"
			},
			{
				"ang": "{16.4941 -0.8049 11.2136}",
				"pos": "[-0.0005 89.4595 0]"
			},
			{
				"ang": "{-31.9311 149.7593 -77.3282}",
				"pos": "[-66.6356 47.4111 36.417]"
			},
			{
				"ang": "{-5.5108 21.7278 71.1101}",
				"pos": "[-0.0003 54.1123 0.001]"
			},
			{
				"ang": "{0 0 -78.4619}",
				"pos": "[-0.0002 75.4209 0.001]"
			},
			{
				"ang": "{-33.6239 17.6425 9.4055}",
				"pos": "[-0.0001 89.459 -0.001]"
			},
			{
				"ang": "{22.8674 166.1996 -32.5781}",
				"pos": "[52.2493 0.0017 0.001]"
			},
			{
				"ang": "{-0 0 57.7815}",
				"pos": "[0 80.4258 -0.0005]"
			},
			{
				"ang": "{13.0113 6.0543 -94.542}",
				"pos": "[-0.0005 78.072 -0.001]"
			},
			{
				"ang": "{-26.2141 139.2561 -6.0269}",
				"pos": "[-52.6133 0.0035 -0.0127]"
			},
			{
				"ang": "{0 0 62.509}",
				"pos": "[0.0002 80.4246 0.001]"
			},
			{
				"ang": "{4.5429 32.4114 -94.9943}",
				"pos": "[-0.0005 78.0718 0]"
			},
			{
				"ang": "{0.6611 1.0359 -22.2461}",
				"pos": "[-15.4529 200 91.9375]"
			}
		],
		[
			{
				"ang": "{0 -20.0801 0}",
				"pos": "[-60.0371 0 0]"
			},
			{
				"ang": "{-5.0283 -30.1373 99.0942}",
				"pos": "[42.6702 -99.7148 148.415]"
			},
			{
				"ang": "{7.6845 -1.8923 -33.2831}",
				"pos": "[0.0007 27.0679 -0.001]"
			},
			{
				"ang": "{13.0037 -2.2808 -35.2583}",
				"pos": "[0.0004 85.0156 0.001]"
			},
			{
				"ang": "{6.1836 -174.1193 -179.4832}",
				"pos": "[-0.0006 80.8457 18.2988]"
			},
			{
				"ang": "{10.1518 -6.6375 36.3559}",
				"pos": "[0.0007 48.6123 0.0005]"
			},
			{
				"ang": "{-9.2236 2.8277 9.0748}",
				"pos": "[0 32.1201 0]"
			},
			{
				"ang": "{-2.1174 177.7268 3.5122}",
				"pos": "[-19.1274 15.8936 14.8352]"
			},
			{
				"ang": "{-2.8672 -179.4918 -176.6079}",
				"pos": "[19.1272 15.8926 14.8359]"
			},
			{
				"ang": "{29.1771 -149.2742 -110.7841}",
				"pos": "[60.7617 55.4658 30.2461]"
			},
			{
				"ang": "{11.001 -43.6837 64.8539}",
				"pos": "[0 54.1123 0.001]"
			},
			{
				"ang": "{0 0 -75.4129}",
				"pos": "[0.001 75.4197 0]"
			},
			{
				"ang": "{13.1182 -1.3529 12.2941}",
				"pos": "[-0.001 89.4595 0]"
			},
			{
				"ang": "{-32.0488 149.755 -77.6144}",
				"pos": "[-66.3656 46.6133 35.7803]"
			},
			{
				"ang": "{-5.8629 20.8395 70.1286}",
				"pos": "[-0 54.1123 0]"
			},
			{
				"ang": "{0 0 -75.6277}",
				"pos": "[-0.0004 75.4189 0.0005]"
			},
			{
				"ang": "{-31.4073 16.8845 9.2552}",
				"pos": "[0.0002 89.459 -0.001]"
			},
			{
				"ang": "{23.7761 170.2703 -30.1784}",
				"pos": "[52.2498 0.0018 0.001]"
			},
			{
				"ang": "{0 0 64.2376}",
				"pos": "[0.0005 80.4253 -0.0005]"
			},
			{
				"ang": "{12.7003 2.464 -98.7158}",
				"pos": "[0 78.0718 0]"
			},
			{
				"ang": "{-24.3593 139.8737 -0.4784}",
				"pos": "[-52.613 0.0037 -0.0137]"
			},
			{
				"ang": "{-0 0 58.4769}",
				"pos": "[0.0005 80.425 0]"
			},
			{
				"ang": "{1.9462 32.3509 -98.3425}",
				"pos": "[0 78.0718 0]"
			},
			{
				"ang": "{0.6611 1.0359 -22.2461}",
				"pos": "[-15.4531 200 91.9375]"
			}
		],
		[
			{
				"ang": "{0 -11.2917 0.0029}",
				"pos": "[-71.6152 0 0]"
			},
			{
				"ang": "{-6.1709 -31.395 101.8027}",
				"pos": "[35.0044 -95.0752 143.4253]"
			},
			{
				"ang": "{8.0222 1.6725 -34.7721}",
				"pos": "[-0.0004 27.0679 -0.001]"
			},
			{
				"ang": "{10.9412 -2.3641 -37.0694}",
				"pos": "[0.0003 85.0161 0]"
			},
			{
				"ang": "{5.0834 -172.3231 178.9416}",
				"pos": "[-0.0002 80.8467 18.2988]"
			},
			{
				"ang": "{13.2332 -5.1365 33.4553}",
				"pos": "[0 48.6123 0]"
			},
			{
				"ang": "{-8.0438 3.2045 9.843}",
				"pos": "[0 32.1221 -0.0001]"
			},
			{
				"ang": "{-2.226 177.7593 3.8508}",
				"pos": "[-19.127 15.8936 14.8352]"
			},
			{
				"ang": "{-2.9921 -179.4625 -176.2759}",
				"pos": "[19.1279 15.8945 14.8358]"
			},
			{
				"ang": "{29.0441 -149.1929 -112.7442}",
				"pos": "[62.1218 54.7295 28.2485]"
			},
			{
				"ang": "{12.295 -44.1308 67.059}",
				"pos": "[0.0005 54.1123 0]"
			},
			{
				"ang": "{0 0 -80.1904}",
				"pos": "[0 75.4199 -0.0005]"
			},
			{
				"ang": "{10.7738 -4.1933 11.0877}",
				"pos": "[0 89.46 -0.0002]"
			},
			{
				"ang": "{-32.789 149.7562 -79.4108}",
				"pos": "[-65.6565 45.8262 35.2935]"
			},
			{
				"ang": "{-6.1447 18.4758 76.1183}",
				"pos": "[-0.0002 54.1123 0]"
			},
			{
				"ang": "{0 0 -82.806}",
				"pos": "[0 75.4199 0.0005]"
			},
			{
				"ang": "{-29.6908 12.0417 14.5763}",
				"pos": "[0 89.459 0]"
			},
			{
				"ang": "{26.6203 177.1946 -26.7656}",
				"pos": "[52.2494 0.0017 0.002]"
			},
			{
				"ang": "{0 0 73.5795}",
				"pos": "[-0.0005 80.4248 0]"
			},
			{
				"ang": "{11.1576 -4.625 -103.2484}",
				"pos": "[-0.0005 78.0718 0.001]"
			},
			{
				"ang": "{-18.0274 142.7778 -8.1823}",
				"pos": "[-52.6132 0.0037 -0.0127]"
			},
			{
				"ang": "{0 0 70.2803}",
				"pos": "[-0.0005 80.4255 -0.001]"
			},
			{
				"ang": "{2.2013 31.4534 -104.688}",
				"pos": "[0.0005 78.0723 0.0005]"
			},
			{
				"ang": "{0.6611 1.0359 -22.2461}",
				"pos": "[-15.4526 199.999 91.9375]"
			}
		],
		[
			{
				"ang": "{0 -4.7028 0.0062}",
				"pos": "[-75.9224 0 0]"
			},
			{
				"ang": "{-6.4777 -30.8508 102.4037}",
				"pos": "[23.8882 -91.8672 140.3776]"
			},
			{
				"ang": "{8.0513 4.621 -35.2883}",
				"pos": "[0.0005 27.0679 0.001]"
			},
			{
				"ang": "{8.7253 -2.1443 -37.4909}",
				"pos": "[-0.0007 85.0159 0]"
			},
			{
				"ang": "{3.5051 -169.7803 179.0457}",
				"pos": "[0 80.8457 18.2993]"
			},
			{
				"ang": "{14.6285 -2.825 30.6409}",
				"pos": "[0 48.6123 0]"
			},
			{
				"ang": "{-6.8926 3.7367 10.1732}",
				"pos": "[0.0005 32.1211 0]"
			},
			{
				"ang": "{-2.2823 177.8088 4.1099}",
				"pos": "[-19.1279 15.8936 14.8353]"
			},
			{
				"ang": "{-3.0612 -179.4172 -176.0196}",
				"pos": "[19.127 15.8936 14.8359]"
			},
			{
				"ang": "{28.7448 -149.0633 -114.2041}",
				"pos": "[63.1331 53.7129 26.9331]"
			},
			{
				"ang": "{12.1071 -42.7068 70.1776}",
				"pos": "[0 54.1123 -0.0002]"
			},
			{
				"ang": "{0 0 -82.0092}",
				"pos": "[0.001 75.4197 0]"
			},
			{
				"ang": "{11.7075 -7.5307 7.6356}",
				"pos": "[-0.001 89.459 0.0002]"
			},
			{
				"ang": "{-34.1554 149.8418 -83.1315}",
				"pos": "[-64.9736 45.4912 35.1685]"
			},
			{
				"ang": "{-6.4919 17.6723 83.1676}",
				"pos": "[0 54.1123 -0.001]"
			},
			{
				"ang": "{0 0 -90.303}",
				"pos": "[0.0004 75.418 0]"
			},
			{
				"ang": "{-29.649 10.5884 18.4113}",
				"pos": "[0 89.4595 0]"
			},
			{
				"ang": "{29.6027 -176.1259 -24.8156}",
				"pos": "[52.2496 0.0017 0.002]"
			},
			{
				"ang": "{0 0 80.3986}",
				"pos": "[0 80.4253 0.0005]"
			},
			{
				"ang": "{10.1518 -9.4825 -102.6502}",
				"pos": "[0 78.0718 0]"
			},
			{
				"ang": "{-13.6624 147.5109 -16.0676}",
				"pos": "[-52.6123 0.0037 -0.0127]"
			},
			{
				"ang": "{0 0 78.2861}",
				"pos": "[-0.0005 80.4258 -0.001]"
			},
			{
				"ang": "{1.2822 29.5165 -108.6122}",
				"pos": "[0 78.0713 -0.0005]"
			},
			{
				"ang": "{0.6611 1.0359 -22.2461}",
				"pos": "[-15.4526 199.999 91.9375]"
			}
		],
		[
			{
				"ang": "{-0 1.9179 0.0194}",
				"pos": "[-80.7124 0 0]"
			},
			{
				"ang": "{-5.9362 -29.7607 102.698}",
				"pos": "[13.1743 -87.1387 139.0356]"
			},
			{
				"ang": "{7.8688 6.8404 -35.6726}",
				"pos": "[0 27.0676 -0.001]"
			},
			{
				"ang": "{6.6347 -1.9488 -37.7144}",
				"pos": "[0.0002 85.0156 0.001]"
			},
			{
				"ang": "{2.2956 -168.8785 179.2806}",
				"pos": "[0 80.8457 18.2993]"
			},
			{
				"ang": "{15.5734 -1.8106 28.5339}",
				"pos": "[0 48.6123 0.0005]"
			},
			{
				"ang": "{-5.6138 4.1503 10.2063}",
				"pos": "[0.0005 32.1201 0]"
			},
			{
				"ang": "{-2.3232 177.8867 4.3672}",
				"pos": "[-19.127 15.8936 14.8351]"
			},
			{
				"ang": "{-3.113 -179.3438 -175.7634}",
				"pos": "[19.1274 15.8936 14.8358]"
			},
			{
				"ang": "{28.1965 -148.8461 -115.5315}",
				"pos": "[64.043 52.1504 25.4243]"
			},
			{
				"ang": "{11.6219 -40.6714 73.8861}",
				"pos": "[0 54.1123 0.0009]"
			},
			{
				"ang": "{0 0 -83.0802}",
				"pos": "[0 75.42 0]"
			},
			{
				"ang": "{12.9248 -9.9075 4.5357}",
				"pos": "[0 89.459 -0.0002]"
			},
			{
				"ang": "{-35.7416 150.1092 -88.0666}",
				"pos": "[-64.3179 45.2217 35.002]"
			},
			{
				"ang": "{-7.2904 19.619 87.8175}",
				"pos": "[-0.0005 54.1123 0]"
			},
			{
				"ang": "{0 0 -94.4946}",
				"pos": "[-0.0002 75.4209 0.0005]"
			},
			{
				"ang": "{-29.776 9.2691 20.7942}",
				"pos": "[0.0002 89.459 0]"
			},
			{
				"ang": "{31.3479 -167.7376 -22.5863}",
				"pos": "[52.2488 0.0015 0.001]"
			},
			{
				"ang": "{0 0 86.5796}",
				"pos": "[0 80.4263 0]"
			},
			{
				"ang": "{9.0314 -13.7527 -96.7184}",
				"pos": "[-0.0005 78.0728 -0.0005]"
			},
			{
				"ang": "{-9.4837 153.914 -22.4037}",
				"pos": "[-52.613 0.0034 -0.0137]"
			},
			{
				"ang": "{0 0 82.9975}",
				"pos": "[0 80.4253 0]"
			},
			{
				"ang": "{-1.2059 26.7938 -111.0471}",
				"pos": "[-0.0005 78.0723 0]"
			},
			{
				"ang": "{0.6611 1.0359 -22.2461}",
				"pos": "[-15.4531 200 91.9375]"
			}
		],
		[
			{
				"ang": "{-0 8.5189 0.0173}",
				"pos": "[-86.0249 0 0]"
			},
			{
				"ang": "{-5.5447 -28.2343 102.6122}",
				"pos": "[3.8994 -81.5054 139.6562]"
			},
			{
				"ang": "{7.158 7.6288 -35.7705}",
				"pos": "[0.0005 27.0679 0]"
			},
			{
				"ang": "{4.7503 -1.8548 -37.6728}",
				"pos": "[-0.0005 85.0156 0]"
			},
			{
				"ang": "{1.4073 -169.6837 179.6924}",
				"pos": "[-0.0005 80.8477 18.2988]"
			},
			{
				"ang": "{15.8707 -2.2456 27.5998}",
				"pos": "[0.0005 48.6118 0]"
			},
			{
				"ang": "{-4.3287 4.4542 9.8877}",
				"pos": "[0 32.1206 0.0001]"
			},
			{
				"ang": "{-2.3335 177.9615 4.6198}",
				"pos": "[-19.1274 15.8936 14.8352]"
			},
			{
				"ang": "{-3.136 -179.2718 -175.5114}",
				"pos": "[19.1274 15.8926 14.8358]"
			},
			{
				"ang": "{27.7049 -148.6527 -116.1478}",
				"pos": "[64.7109 50.4629 24.0054]"
			},
			{
				"ang": "{9.9441 -37.9921 75.988}",
				"pos": "[-0.0005 54.1123 -0]"
			},
			{
				"ang": "{0 0 -82.6836}",
				"pos": "[0.001 75.42 0.0005]"
			},
			{
				"ang": "{15.1372 -11.5452 3.2735}",
				"pos": "[-0.002 89.4595 0.0001]"
			},
			{
				"ang": "{-37.1556 150.5402 -93.2624}",
				"pos": "[-63.9399 45.2891 34.4233]"
			},
			{
				"ang": "{-8.5852 23.8517 89.3414}",
				"pos": "[0 54.1128 -0.001]"
			},
			{
				"ang": "{0 0 -95.4244}",
				"pos": "[0.0002 75.4199 0]"
			},
			{
				"ang": "{-29.402 7.8 21.2126}",
				"pos": "[0.0005 89.459 -0.001]"
			},
			{
				"ang": "{32.4147 -160.2927 -20.7773}",
				"pos": "[52.2495 0.0015 0.002]"
			},
			{
				"ang": "{0 0 90.3752}",
				"pos": "[0.0007 80.4258 0]"
			},
			{
				"ang": "{7.8994 -17.5664 -85.5961}",
				"pos": "[-0.0002 78.0713 -0.0005]"
			},
			{
				"ang": "{-5.6011 160.2607 -27.1876}",
				"pos": "[-52.613 0.0034 -0.0137]"
			},
			{
				"ang": "{0 0 84.6755}",
				"pos": "[0.0005 80.4253 0]"
			},
			{
				"ang": "{-4.4078 23.3766 -111.5368}",
				"pos": "[-0.0005 78.0713 0]"
			},
			{
				"ang": "{0.6611 1.0359 -22.2461}",
				"pos": "[-15.4531 199.9995 91.9375]"
			}
		],
		[
			{
				"ang": "{-0 15.081 0.0167}",
				"pos": "[-91.7368 0 0]"
			},
			{
				"ang": "{-5.6133 -26.4431 102.1074}",
				"pos": "[-3.8164 -75.2944 141.2937]"
			},
			{
				"ang": "{6.1033 7.4946 -35.5158}",
				"pos": "[0 27.0676 0]"
			},
			{
				"ang": "{3.0522 -1.8199 -37.416}",
				"pos": "[-0.0005 85.0154 0]"
			},
			{
				"ang": "{0.5749 -171.0576 -179.699}",
				"pos": "[-0.0005 80.8467 18.2988]"
			},
			{
				"ang": "{15.6255 -2.9915 27.38}",
				"pos": "[0.0005 48.6118 0]"
			},
			{
				"ang": "{-3.012 4.7088 9.5087}",
				"pos": "[0.001 32.1221 -0]"
			},
			{
				"ang": "{-2.3152 178.0134 4.8674}",
				"pos": "[-19.1279 15.894 14.835]"
			},
			{
				"ang": "{-3.1302 -179.2225 -175.2632}",
				"pos": "[19.126 15.8936 14.8357]"
			},
			{
				"ang": "{27.6102 -148.6343 -115.8304}",
				"pos": "[65.1699 48.9951 22.8828]"
			},
			{
				"ang": "{7.0952 -35.0741 77.2524}",
				"pos": "[0 54.1123 0]"
			},
			{
				"ang": "{0 0 -80.9763}",
				"pos": "[-0.001 75.4198 -0.0005]"
			},
			{
				"ang": "{17.8964 -13.2478 2.3939}",
				"pos": "[0.001 89.459 0.0009]"
			},
			{
				"ang": "{-38.1423 151.0168 -97.8389}",
				"pos": "[-63.9785 45.8228 33.3325]"
			},
			{
				"ang": "{-9.8055 29.2062 88.3663}",
				"pos": "[-0.0005 54.1123 0]"
			},
			{
				"ang": "{0 0 -95.0431}",
				"pos": "[-0.0005 75.4209 0.0005]"
			},
			{
				"ang": "{-28.452 6.0714 20.5741}",
				"pos": "[0.0002 89.4595 0]"
			},
			{
				"ang": "{32.3728 -159.3874 -23.9121}",
				"pos": "[52.249 0.0017 0.001]"
			},
			{
				"ang": "{0 0 94.4754}",
				"pos": "[0.0002 80.4258 0.0005]"
			},
			{
				"ang": "{8.2836 -18.5942 -80.096}",
				"pos": "[-0.0007 78.0723 0]"
			},
			{
				"ang": "{-2.1389 165.8157 -30.8007}",
				"pos": "[-52.6133 0.0037 -0.0127]"
			},
			{
				"ang": "{0 0 84.6836}",
				"pos": "[0 80.4258 0]"
			},
			{
				"ang": "{-7.3411 19.3014 -110.7231}",
				"pos": "[0 78.0718 -0.0005]"
			},
			{
				"ang": "{0.6611 1.0359 -22.2461}",
				"pos": "[-15.4531 199.9995 91.9375]"
			}
		],
		[
			{
				"ang": "{-0 21.5716 0.0042}",
				"pos": "[-97.8467 0 0]"
			},
			{
				"ang": "{-5.5307 -24.5505 101.2426}",
				"pos": "[-10.3447 -68.5234 143.8835]"
			},
			{
				"ang": "{4.989 7.1017 -34.9931}",
				"pos": "[0 27.0679 -0.001]"
			},
			{
				"ang": "{1.509 -1.7885 -37.0365}",
				"pos": "[0 85.0156 -0.001]"
			},
			{
				"ang": "{-0.2104 -172.7696 -178.9184}",
				"pos": "[-0.001 80.8472 18.2993]"
			},
			{
				"ang": "{14.8931 -3.8824 27.4592}",
				"pos": "[0 48.6123 0.0005]"
			},
			{
				"ang": "{-1.6896 4.9002 9.4896}",
				"pos": "[0.001 32.1206 0]"
			},
			{
				"ang": "{-2.2688 178.0312 5.1089}",
				"pos": "[-19.1279 15.8926 14.8353]"
			},
			{
				"ang": "{-3.0951 -179.2093 -175.0207}",
				"pos": "[19.127 15.8931 14.8358]"
			},
			{
				"ang": "{28.1071 -148.8425 -114.5525}",
				"pos": "[65.4971 47.9556 22.2139]"
			},
			{
				"ang": "{4.1122 -32.7509 78.1552}",
				"pos": "[-0.0005 54.1113 0.0002]"
			},
			{
				"ang": "{0 0 -78.2737}",
				"pos": "[0.001 75.4199 -0.0005]"
			},
			{
				"ang": "{19.8492 -14.843 1.1898}",
				"pos": "[-0.001 89.4585 0.0001]"
			},
			{
				"ang": "{-38.8502 151.5009 -102.0099}",
				"pos": "[-64.2173 46.5938 31.9673]"
			},
			{
				"ang": "{-10.3094 34.8769 85.3692}",
				"pos": "[0.0005 54.1128 0.001]"
			},
			{
				"ang": "{0 0 -93.0302}",
				"pos": "[-0.0005 75.4194 -0.0005]"
			},
			{
				"ang": "{-27.9556 4.8296 18.7633}",
				"pos": "[0.0005 89.459 0.0005]"
			},
			{
				"ang": "{32.1786 -163.4846 -32.7582}",
				"pos": "[52.249 0.002 0.002]"
			},
			{
				"ang": "{0 0 98.5069}",
				"pos": "[0.0002 80.4248 0]"
			},
			{
				"ang": "{10.5246 -15.9193 -77.9032}",
				"pos": "[0.0002 78.0718 -0.002]"
			},
			{
				"ang": "{0.6558 171.2978 -32.7317}",
				"pos": "[-52.6133 0.0039 -0.0137]"
			},
			{
				"ang": "{-0 0 82.6783}",
				"pos": "[0 80.4253 0]"
			},
			{
				"ang": "{-9.8774 14.485 -108.792}",
				"pos": "[0.0005 78.0718 0]"
			},
			{
				"ang": "{0.6611 1.0359 -22.2461}",
				"pos": "[-15.4531 200 91.9375]"
			}
		],
		[
			{
				"ang": "{-0 27.9566 0}",
				"pos": "[-104.333 0 0]"
			},
			{
				"ang": "{-5.136 -22.5573 99.5775}",
				"pos": "[-15.5771 -61.7358 147.1168]"
			},
			{
				"ang": "{3.7568 6.6077 -33.9669}",
				"pos": "[-0.001 27.0679 0]"
			},
			{
				"ang": "{0.0017 -1.6631 -36.3963}",
				"pos": "[-0.001 85.0161 -0.001]"
			},
			{
				"ang": "{-0.9255 -174.7988 -177.8247}",
				"pos": "[0 80.8462 18.2993]"
			},
			{
				"ang": "{13.7472 -5.0539 27.6935}",
				"pos": "[0.001 48.6123 -0.0005]"
			},
			{
				"ang": "{-0.3436 5.0154 9.7152}",
				"pos": "[-0.001 32.1206 0]"
			},
			{
				"ang": "{-2.1899 178.0058 5.3382}",
				"pos": "[-19.127 15.8926 14.8351]"
			},
			{
				"ang": "{-3.028 -179.2374 -174.7867}",
				"pos": "[19.127 15.8931 14.8358]"
			},
			{
				"ang": "{29.4121 -149.3211 -112.0798}",
				"pos": "[65.5957 47.499 22.3154]"
			},
			{
				"ang": "{2.1314 -31.532 79.3209}",
				"pos": "[0.0005 54.1113 0]"
			},
			{
				"ang": "{0 0 -75.687}",
				"pos": "[0 75.4202 0.0005]"
			},
			{
				"ang": "{19.6873 -15.9219 -0.1671}",
				"pos": "[0 89.459 0.0002]"
			},
			{
				"ang": "{-39.3069 151.9461 -105.7053}",
				"pos": "[-64.5 47.5576 30.6729]"
			},
			{
				"ang": "{-9.7441 40.2443 80.511}",
				"pos": "[0.0005 54.1128 -0.001]"
			},
			{
				"ang": "{0 0 -88.6018}",
				"pos": "[0 75.4204 0]"
			},
			{
				"ang": "{-28.2948 4.4204 15.5566}",
				"pos": "[0.0005 89.458 0]"
			},
			{
				"ang": "{31.4634 -168.3051 -42.5478}",
				"pos": "[52.249 0.0017 0.002]"
			},
			{
				"ang": "{0 0 96.9087}",
				"pos": "[0.0005 80.4258 -0.0005]"
			},
			{
				"ang": "{12.8771 -11.1546 -71.9254}",
				"pos": "[-0.0005 78.0718 0]"
			},
			{
				"ang": "{2.4376 176.7004 -33.3754}",
				"pos": "[-52.6133 0.0037 -0.0127]"
			},
			{
				"ang": "{0 0 78.585}",
				"pos": "[-0.0005 80.4258 0]"
			},
			{
				"ang": "{-11.5201 8.8982 -105.7406}",
				"pos": "[0.001 78.0723 0.0005]"
			},
			{
				"ang": "{0.6611 1.0359 -22.2461}",
				"pos": "[-15.4531 199.9995 91.9375]"
			}
		],
		[
			{
				"ang": "{-0 34.2048 0}",
				"pos": "[-111.1841 0 0]"
			},
			{
				"ang": "{-4.4598 -20.1555 97.0414}",
				"pos": "[-20.002 -55.2949 150.1044]"
			},
			{
				"ang": "{2.415 6.1377 -32.4222}",
				"pos": "[0.001 27.0677 -0.001]"
			},
			{
				"ang": "{-1.5247 -1.3874 -35.4762}",
				"pos": "[-0.001 85.0156 -0.0005]"
			},
			{
				"ang": "{-1.5353 -176.9655 -176.4642}",
				"pos": "[-0.002 80.8467 18.2988]"
			},
			{
				"ang": "{12.3539 -6.1352 28.2802}",
				"pos": "[0 48.6123 0]"
			},
			{
				"ang": "{1.0591 5.134 9.8462}",
				"pos": "[-0.001 32.1211 0]"
			},
			{
				"ang": "{-2.0863 177.9505 5.557}",
				"pos": "[-19.1279 15.8936 14.8351]"
			},
			{
				"ang": "{-2.9349 -179.2954 -174.563}",
				"pos": "[19.127 15.8931 14.8359]"
			},
			{
				"ang": "{30.8326 -149.7684 -108.9964}",
				"pos": "[65.3857 47.229 23.2515]"
			},
			{
				"ang": "{1.0051 -30.1976 81.4475}",
				"pos": "[0 54.1133 -0.0002]"
			},
			{
				"ang": "{0 0 -73.3531}",
				"pos": "[0 75.4199 -0.0005]"
			},
			{
				"ang": "{18.2012 -16.89 -2.2624}",
				"pos": "[0 89.459 0]"
			},
			{
				"ang": "{-39.495 152.2816 -108.6984}",
				"pos": "[-64.6533 48.6055 29.7725]"
			},
			{
				"ang": "{-8.0295 45.2743 74.8543}",
				"pos": "[0.0005 54.1125 0]"
			},
			{
				"ang": "{0 0 -83.1784}",
				"pos": "[0 75.4194 0.001]"
			},
			{
				"ang": "{-28.9362 4.166 11.7562}",
				"pos": "[0 89.459 0]"
			},
			{
				"ang": "{29.643 -170.2932 -49.4421}",
				"pos": "[52.25 0.0017 0.001]"
			},
			{
				"ang": "{0 0 92.0951}",
				"pos": "[0 80.4258 0]"
			},
			{
				"ang": "{12.3965 -7.975 -65.8178}",
				"pos": "[0.0005 78.0723 -0.001]"
			},
			{
				"ang": "{3.611 -178.0365 -33.6439}",
				"pos": "[-52.6123 0.0035 -0.0142]"
			},
			{
				"ang": "{0 0 73.4094}",
				"pos": "[-0.001 80.4258 0]"
			},
			{
				"ang": "{-11.8872 2.7513 -102.0937}",
				"pos": "[0.001 78.0713 -0.001]"
			},
			{
				"ang": "{0.6611 1.0359 -22.2461}",
				"pos": "[-15.4531 200 91.9375]"
			}
		],
		[
			{
				"ang": "{-0 40.2917 0.0073}",
				"pos": "[-118.3081 0 0]"
			},
			{
				"ang": "{-3.4211 -17.297 94.2701}",
				"pos": "[-23.166 -49.2041 152.3929]"
			},
			{
				"ang": "{1.1149 5.7628 -30.8317}",
				"pos": "[0.001 27.0677 -0.0005]"
			},
			{
				"ang": "{-2.9782 -0.9863 -34.5113}",
				"pos": "[0 85.0157 0.0005]"
			},
			{
				"ang": "{-2.0833 -179.26 -175.029}",
				"pos": "[0 80.8469 18.2993]"
			},
			{
				"ang": "{10.5594 -6.7295 29.1775}",
				"pos": "[-0.001 48.6118 0]"
			},
			{
				"ang": "{2.4717 5.0281 9.7607}",
				"pos": "[0.001 32.1213 0]"
			},
			{
				"ang": "{-1.9612 177.881 5.7654}",
				"pos": "[-19.1279 15.8936 14.8349]"
			},
			{
				"ang": "{-2.8187 -179.3695 -174.3497}",
				"pos": "[19.127 15.894 14.8357]"
			},
			{
				"ang": "{32.1876 -150.1056 -105.4458}",
				"pos": "[64.9307 46.9541 24.7871]"
			},
			{
				"ang": "{0.546 -28.5807 84.218}",
				"pos": "[0 54.1133 0.0002]"
			},
			{
				"ang": "{0 0 -71.9081}",
				"pos": "[-0.001 75.4194 0]"
			},
			{
				"ang": "{16.2181 -17.2844 -4.4357}",
				"pos": "[0.001 89.4595 0.0002]"
			},
			{
				"ang": "{-39.3819 152.4469 -110.774}",
				"pos": "[-64.5498 49.4822 29.4595]"
			},
			{
				"ang": "{-4.9426 49.7794 69.4541}",
				"pos": "[0 54.1123 -0.001]"
			},
			{
				"ang": "{0 0 -78.2053}",
				"pos": "[0 75.4204 0.001]"
			},
			{
				"ang": "{-29.491 3.4622 7.8309}",
				"pos": "[-0.0005 89.46 0]"
			},
			{
				"ang": "{27.0747 -169.1358 -53.329}",
				"pos": "[52.25 0.0017 0.0015]"
			},
			{
				"ang": "{0 0 86.3584}",
				"pos": "[0 80.4248 0.0002]"
			},
			{
				"ang": "{10.0242 -7.6996 -61.7107}",
				"pos": "[0.0005 78.0718 0]"
			},
			{
				"ang": "{4.126 -173.0148 -33.0971}",
				"pos": "[-52.6123 0.0037 -0.0142]"
			},
			{
				"ang": "{0 0 67.8127}",
				"pos": "[0 80.4253 -0.0002]"
			},
			{
				"ang": "{-10.5393 -3.5403 -98.6885}",
				"pos": "[0 78.0719 0.0005]"
			},
			{
				"ang": "{0.6611 1.0359 -22.2461}",
				"pos": "[-15.4531 200 91.9375]"
			}
		],
		[
			{
				"ang": "{-0 46.1624 0.007}",
				"pos": "[-125.7573 0 0]"
			},
			{
				"ang": "{-2.0724 -14.1376 92.0069}",
				"pos": "[-24.0986 -43.5688 153.7827]"
			},
			{
				"ang": "{-0.0007 5.537 -29.8582}",
				"pos": "[0.001 27.0679 -0.0005]"
			},
			{
				"ang": "{-4.2437 -0.469 -33.8227}",
				"pos": "[0 85.0158 0]"
			},
			{
				"ang": "{-2.7391 177.9358 -173.6056}",
				"pos": "[0.001 80.8469 18.2988]"
			},
			{
				"ang": "{8.0005 -6.639 30.0241}",
				"pos": "[0 48.6125 0.0002]"
			},
			{
				"ang": "{3.7655 3.9569 9.4482}",
				"pos": "[-0.001 32.1211 0.0001]"
			},
			{
				"ang": "{-1.8109 177.8105 5.9615}",
				"pos": "[-19.1279 15.8936 14.835]"
			},
			{
				"ang": "{-2.6791 -179.4447 -174.1458}",
				"pos": "[19.127 15.8933 14.8358]"
			},
			{
				"ang": "{33.378 -150.2928 -101.4178}",
				"pos": "[64.2646 46.5669 26.812]"
			},
			{
				"ang": "{0.7911 -26.9882 86.9831}",
				"pos": "[0 54.1123 0]"
			},
			{
				"ang": "{0 0 -71.9643}",
				"pos": "[0 75.4194 -0.0005]"
			},
			{
				"ang": "{14.302 -16.5386 -6.3247}",
				"pos": "[0 89.4585 0]"
			},
			{
				"ang": "{-38.8602 152.3411 -111.5163}",
				"pos": "[-64.0791 49.9451 29.8398]"
			},
			{
				"ang": "{-0.2664 52.1155 65.9959}",
				"pos": "[0 54.1132 -0.0005]"
			},
			{
				"ang": "{0 0 -75.4711}",
				"pos": "[0 75.4197 0.001]"
			},
			{
				"ang": "{-30.355 3.5252 4.0636}",
				"pos": "[0 89.459 0.0005]"
			},
			{
				"ang": "{24.1213 -166.1249 -54.3163}",
				"pos": "[52.25 0.0017 0.0017]"
			},
			{
				"ang": "{0 0 81.0263}",
				"pos": "[0 80.4258 0.0001]"
			},
			{
				"ang": "{7.0632 -9.7932 -61.3005}",
				"pos": "[0 78.0718 0.001]"
			},
			{
				"ang": "{4.3685 -168.6873 -31.0578}",
				"pos": "[-52.6123 0.0037 -0.0134]"
			},
			{
				"ang": "{-0 0 62.4501}",
				"pos": "[0 80.4253 -0.0002]"
			},
			{
				"ang": "{-7.9519 -8.8182 -96.5281}",
				"pos": "[0 78.072 0]"
			},
			{
				"ang": "{0.6611 1.0359 -22.2461}",
				"pos": "[-15.4531 200.0005 91.9375]"
			}
		],
		[
			{
				"ang": "{-0 51.9319 0}",
				"pos": "[-133.5688 0 0]"
			},
			{
				"ang": "{-0.7 -10.6268 90.2673}",
				"pos": "[-23.002 -38.8911 154.4628]"
			},
			{
				"ang": "{-1.1028 5.4141 -29.4286}",
				"pos": "[0.001 27.0678 0.0002]"
			},
			{
				"ang": "{-5.5257 0.1821 -33.4771}",
				"pos": "[-0.001 85.0153 -0.0002]"
			},
			{
				"ang": "{-3.3708 174.5946 -172.4674}",
				"pos": "[0 80.8464 18.2993]"
			},
			{
				"ang": "{5.2186 -6.2638 30.5849}",
				"pos": "[0 48.6125 0.0002]"
			},
			{
				"ang": "{4.9805 2.2507 9.1516}",
				"pos": "[0.001 32.1211 0.0001]"
			},
			{
				"ang": "{-1.6406 177.7509 6.1488}",
				"pos": "[-19.1289 15.8933 14.8352]"
			},
			{
				"ang": "{-2.5177 -179.507 -173.9503}",
				"pos": "[19.127 15.8933 14.8359]"
			},
			{
				"ang": "{34.3654 -150.3363 -96.9338}",
				"pos": "[63.4814 46.0656 29.1133]"
			},
			{
				"ang": "{1.6449 -25.7083 88.5094}",
				"pos": "[0 54.1123 0.0005]"
			},
			{
				"ang": "{0 0 -72.6678}",
				"pos": "[0.001 75.4204 0]"
			},
			{
				"ang": "{12.7108 -14.9905 -8.0469}",
				"pos": "[0 89.4585 0.0005]"
			},
			{
				"ang": "{-38.0461 152.0545 -111.3349}",
				"pos": "[-63.3682 50.1117 30.5491]"
			},
			{
				"ang": "{4.7585 51.9379 64.2159}",
				"pos": "[-0.001 54.1127 0]"
			},
			{
				"ang": "{0 0 -75.1596}",
				"pos": "[-0.0005 75.4204 0]"
			},
			{
				"ang": "{-30.6353 3.9142 2.054}",
				"pos": "[0 89.459 0]"
			},
			{
				"ang": "{20.6458 -165.9281 -56.6023}",
				"pos": "[52.25 0.0017 0.0015]"
			},
			{
				"ang": "{0 0 76.8432}",
				"pos": "[-0.001 80.4258 -0.0003]"
			},
			{
				"ang": "{5.8848 -10.27 -62.7719}",
				"pos": "[0.001 78.0719 0]"
			},
			{
				"ang": "{4.944 -165.389 -28.4086}",
				"pos": "[-52.6133 0.0036 -0.0131]"
			},
			{
				"ang": "{0 0 58.0946}",
				"pos": "[0 80.4258 0.0002]"
			},
			{
				"ang": "{-5.1001 -12.7529 -95.6199}",
				"pos": "[-0.001 78.0719 0]"
			},
			{
				"ang": "{0.6611 1.0359 -22.2461}",
				"pos": "[-15.4541 200 91.9375]"
			}
		],
		[
			{
				"ang": "{-0 57.3261 0}",
				"pos": "[-141.2393 0 0]"
			},
			{
				"ang": "{0.2872 -6.7825 89.4542}",
				"pos": "[-19.9521 -35.3276 154.437]"
			},
			{
				"ang": "{-2.286 5.3264 -29.6426}",
				"pos": "[0.001 27.0678 0]"
			},
			{
				"ang": "{-6.9525 0.9166 -33.6621}",
				"pos": "[0 85.0155 0.0004]"
			},
			{
				"ang": "{-3.3634 170.5949 -171.8507}",
				"pos": "[-0.001 80.8468 18.2988]"
			},
			{
				"ang": "{3.2725 -6.6913 30.7964}",
				"pos": "[0 48.6121 0]"
			},
			{
				"ang": "{6.2145 0.6563 9.1041}",
				"pos": "[0 32.1213 0.0001]"
			},
			{
				"ang": "{-1.4691 177.7136 6.3169}",
				"pos": "[-19.1279 15.8936 14.8353]"
			},
			{
				"ang": "{-2.3547 -179.547 -173.7744}",
				"pos": "[19.126 15.8937 14.8359]"
			},
			{
				"ang": "{35.0223 -150.2407 -92.2442}",
				"pos": "[62.6768 45.4183 31.3689]"
			},
			{
				"ang": "{3.0379 -25.0602 87.5118}",
				"pos": "[0 54.1123 0]"
			},
			{
				"ang": "{0 0 -73.433}",
				"pos": "[0.001 75.4199 0]"
			},
			{
				"ang": "{11.5324 -12.9914 -9.2317}",
				"pos": "[0 89.4585 0]"
			},
			{
				"ang": "{-37.0629 151.6723 -110.4948}",
				"pos": "[-62.5352 49.9169 31.343]"
			},
			{
				"ang": "{8.2591 49.5467 63.5649}",
				"pos": "[-0.001 54.1125 -0.0005]"
			},
			{
				"ang": "{0 0 -76.8575}",
				"pos": "[0 75.4199 -0.002]"
			},
			{
				"ang": "{-29.4231 4.0672 2.9424}",
				"pos": "[-0.0005 89.459 0]"
			},
			{
				"ang": "{16.7106 -167.4253 -58.8834}",
				"pos": "[52.25 0.0017 0.0014]"
			},
			{
				"ang": "{-0 0 71.6774}",
				"pos": "[-0.001 80.4248 0]"
			},
			{
				"ang": "{6.4308 -9.3892 -63.2514}",
				"pos": "[0 78.0721 0.0002]"
			},
			{
				"ang": "{6.0317 -163.5823 -25.6071}",
				"pos": "[-52.6133 0.0036 -0.0126]"
			},
			{
				"ang": "{0 0 55.897}",
				"pos": "[0.001 80.4258 -0.0001]"
			},
			{
				"ang": "{-2.7103 -15.1597 -96.2133}",
				"pos": "[0 78.072 0]"
			},
			{
				"ang": "{0.6611 1.0359 -22.2461}",
				"pos": "[-15.4521 200 91.9375]"
			}
		],
		[
			{
				"ang": "{-0 62.394 0.0026}",
				"pos": "[-149.2949 0 0]"
			},
			{
				"ang": "{1.6063 -1.7834 90.2918}",
				"pos": "[-15.334 -32.0059 153.3822]"
			},
			{
				"ang": "{-3.8285 4.9427 -30.7377}",
				"pos": "[0 27.0679 0]"
			},
			{
				"ang": "{-8.9171 1.5468 -34.9078}",
				"pos": "[0 85.0156 0.0001]"
			},
			{
				"ang": "{-3.1639 167.7832 -172.3918}",
				"pos": "[0 80.8471 18.2991]"
			},
			{
				"ang": "{1.5466 -6.8245 30.8634}",
				"pos": "[0.001 48.6122 0]"
			},
			{
				"ang": "{7.317 -0.1133 9.4535}",
				"pos": "[-0.001 32.1205 0]"
			},
			{
				"ang": "{-1.2975 177.7034 6.4632}",
				"pos": "[-19.126 15.8932 14.8354]"
			},
			{
				"ang": "{-2.1902 -179.5598 -173.6212}",
				"pos": "[19.1279 15.894 14.8358]"
			},
			{
				"ang": "{35.1499 -150.029 -87.0797}",
				"pos": "[61.8779 44.4291 33.2112]"
			},
			{
				"ang": "{4.327 -24.6662 85.2354}",
				"pos": "[-0.0005 54.1123 0.0005]"
			},
			{
				"ang": "{0 0 -78.2563}",
				"pos": "[0 75.4199 0.0005]"
			},
			{
				"ang": "{11.2617 -10.0765 -8.2278}",
				"pos": "[0 89.459 -0.0005]"
			},
			{
				"ang": "{-35.927 151.2361 -109.0602}",
				"pos": "[-61.667 49.1473 31.8557]"
			},
			{
				"ang": "{8.3108 47.6022 63.6313}",
				"pos": "[0 54.1128 0.0005]"
			},
			{
				"ang": "{0 0 -79.9264}",
				"pos": "[0.0005 75.4199 -0.0005]"
			},
			{
				"ang": "{-25.3089 2.2204 6.088}",
				"pos": "[0 89.4585 0.0005]"
			},
			{
				"ang": "{14.3226 -166.5146 -57.7591}",
				"pos": "[52.25 0.0018 0.0015]"
			},
			{
				"ang": "{0 0 66.4147}",
				"pos": "[0 80.4253 0]"
			},
			{
				"ang": "{6.3736 -9.716 -64.443}",
				"pos": "[-0.001 78.0718 0.0001]"
			},
			{
				"ang": "{8.1884 -162.3173 -21.7331}",
				"pos": "[-52.6133 0.0037 -0.0134]"
			},
			{
				"ang": "{0 0 55.6173}",
				"pos": "[0 80.425 -0.0005]"
			},
			{
				"ang": "{-1.0056 -16.2413 -98.0503}",
				"pos": "[0.001 78.0718 -0.0001]"
			},
			{
				"ang": "{0.6611 1.0359 -22.2461}",
				"pos": "[-15.4531 200.0005 91.9375]"
			}
		],
		[
			{
				"ang": "{-0 67.1518 0.0091}",
				"pos": "[-157.3506 0 0]"
			},
			{
				"ang": "{4.7517 4.9666 93.2765}",
				"pos": "[-10.6611 -28.0266 151.606]"
			},
			{
				"ang": "{-5.8814 4.124 -32.7413}",
				"pos": "[0.001 27.0677 0.0005]"
			},
			{
				"ang": "{-11.7038 2.0205 -37.3408}",
				"pos": "[0 85.0153 0.0002]"
			},
			{
				"ang": "{-4.3255 169.0429 -174.5025}",
				"pos": "[0 80.8469 18.299]"
			},
			{
				"ang": "{-2.2747 -3.2971 30.6594}",
				"pos": "[-0.001 48.6123 0.0002]"
			},
			{
				"ang": "{7.5915 -0.6101 10.0978}",
				"pos": "[0 32.1213 0.0001]"
			},
			{
				"ang": "{-1.1274 177.7125 6.5955}",
				"pos": "[-19.127 15.8933 14.835]"
			},
			{
				"ang": "{-2.0273 -179.5519 -173.481}",
				"pos": "[19.127 15.8934 14.8358]"
			},
			{
				"ang": "{34.9541 -149.8125 -82.0952}",
				"pos": "[61.0742 42.9943 34.3286]"
			},
			{
				"ang": "{4.9909 -22.9914 85.4147}",
				"pos": "[0.0005 54.1123 0]"
			},
			{
				"ang": "{0 0 -88.6784}",
				"pos": "[0 75.4204 0.0005]"
			},
			{
				"ang": "{11.8042 -7.1358 -5.5269}",
				"pos": "[-0.001 89.4595 0.0005]"
			},
			{
				"ang": "{-34.7219 150.8056 -107.2453}",
				"pos": "[-60.9375 47.7488 31.7546]"
			},
			{
				"ang": "{5.8254 47.0998 63.8412}",
				"pos": "[0.001 54.1128 0]"
			},
			{
				"ang": "{0 0 -82.4252}",
				"pos": "[-0.001 75.4197 0]"
			},
			{
				"ang": "{-19.9366 0.0936 7.428}",
				"pos": "[0 89.4595 -0.0005]"
			},
			{
				"ang": "{14.4981 -162.0984 -51.7847}",
				"pos": "[52.249 0.0017 0.0015]"
			},
			{
				"ang": "{-0 0 63.7346}",
				"pos": "[-0.001 80.4253 -0.0002]"
			},
			{
				"ang": "{5.373 -11.0133 -69.7399}",
				"pos": "[0.001 78.0718 -0.0001]"
			},
			{
				"ang": "{11.596 -159.2825 -14.9998}",
				"pos": "[-52.6133 0.0035 -0.0132]"
			},
			{
				"ang": "{0 0 54.2897}",
				"pos": "[-0.001 80.4253 -0.0002]"
			},
			{
				"ang": "{0.4881 -16.4292 -99.4085}",
				"pos": "[0 78.0718 -0.0001]"
			},
			{
				"ang": "{0.6611 1.0359 -22.2461}",
				"pos": "[-15.4531 200.0002 91.9375]"
			}
		],
		[
			{
				"ang": "{-0 71.5627 0}",
				"pos": "[-165.4063 0 0]"
			},
			{
				"ang": "{7.8598 10.5771 97.3035}",
				"pos": "[-6.2754 -24.6118 148.1271]"
			},
			{
				"ang": "{-7.5721 2.4671 -34.8409}",
				"pos": "[0 27.068 0.0005]"
			},
			{
				"ang": "{-13.3343 2.4964 -40.2216}",
				"pos": "[0 85.0155 0]"
			},
			{
				"ang": "{-5.4844 171.9633 -176.8327}",
				"pos": "[-0.001 80.8469 18.2991]"
			},
			{
				"ang": "{-7.2306 1.7806 28.6878}",
				"pos": "[0 48.6121 0]"
			},
			{
				"ang": "{7.1216 -1.3157 10.7721}",
				"pos": "[-0.001 32.1205 0]"
			},
			{
				"ang": "{-0.9626 177.752 6.7165}",
				"pos": "[-19.127 15.8931 14.8354]"
			},
			{
				"ang": "{-1.8687 -179.5146 -173.3523}",
				"pos": "[19.127 15.8926 14.8359]"
			},
			{
				"ang": "{34.867 -149.6605 -78.4336}",
				"pos": "[60.1543 41.6357 34.8788]"
			},
			{
				"ang": "{5.5756 -19.9841 88.3949}",
				"pos": "[0.0005 54.1118 0]"
			},
			{
				"ang": "{0 0 -100.7355}",
				"pos": "[-0.001 75.4194 0]"
			},
			{
				"ang": "{13.34 -5.917 -3.9049}",
				"pos": "[0 89.4594 0]"
			},
			{
				"ang": "{-33.505 150.4194 -105.1364}",
				"pos": "[-60.6172 46.2275 31.2558]"
			},
			{
				"ang": "{1.1689 49.0318 66.352}",
				"pos": "[0 54.1123 0.0005]"
			},
			{
				"ang": "{0 0 -86.9158}",
				"pos": "[0 75.4204 0]"
			},
			{
				"ang": "{-13.6127 -2.9502 7.4933}",
				"pos": "[0 89.459 0.0007]"
			},
			{
				"ang": "{14.8792 -158.2958 -44.4605}",
				"pos": "[52.25 0.0016 0.0015]"
			},
			{
				"ang": "{-0 0 63.1506}",
				"pos": "[0.001 80.4257 0]"
			},
			{
				"ang": "{5.0275 -11.1712 -75.5795}",
				"pos": "[0 78.0718 0]"
			},
			{
				"ang": "{13.4493 -155.9687 -8.9574}",
				"pos": "[-52.6133 0.0037 -0.0132]"
			},
			{
				"ang": "{0 0 56.3593}",
				"pos": "[0.001 80.4255 -0.0002]"
			},
			{
				"ang": "{0.9773 -16.0866 -101.8635}",
				"pos": "[0 78.0718 -0.0003]"
			},
			{
				"ang": "{0.6611 1.0359 -22.2461}",
				"pos": "[-15.4521 200.0005 91.9375]"
			}
		],
		[
			{
				"ang": "{-0 75.5452 0.016}",
				"pos": "[-173.5112 0 0]"
			},
			{
				"ang": "{8.9955 12.307 100.1439}",
				"pos": "[-1.2881 -23.2788 140.0174]"
			},
			{
				"ang": "{-8.0701 -0.1571 -36.3912}",
				"pos": "[0 27.0679 0]"
			},
			{
				"ang": "{-12.1054 2.7165 -42.3143}",
				"pos": "[0 85.0154 0.0005]"
			},
			{
				"ang": "{-5.5484 173.1429 -178.3262}",
				"pos": "[-0.001 80.8467 18.2992]"
			},
			{
				"ang": "{-11.34 5.0763 25.4193}",
				"pos": "[0.001 48.6125 0]"
			},
			{
				"ang": "{6.1519 -1.9926 11.2736}",
				"pos": "[0 32.1211 0.0001]"
			},
			{
				"ang": "{-0.8058 177.8218 6.8234}",
				"pos": "[-19.1279 15.8936 14.835]"
			},
			{
				"ang": "{-1.7164 -179.4474 -173.2372}",
				"pos": "[19.1279 15.8938 14.8358]"
			},
			{
				"ang": "{35.4007 -149.5883 -77.2824}",
				"pos": "[59.1338 40.915 35.2874]"
			},
			{
				"ang": "{6.5654 -17.1291 94.4471}",
				"pos": "[-0.0005 54.1123 0.0005]"
			},
			{
				"ang": "{0 0 -112.0891}",
				"pos": "[0 75.4204 0]"
			},
			{
				"ang": "{16.0002 -6.3496 -4.4601}",
				"pos": "[-0.001 89.459 0]"
			},
			{
				"ang": "{-32.3677 150.1079 -102.8237}",
				"pos": "[-60.8662 45.1313 30.8286]"
			},
			{
				"ang": "{-3.9937 51.493 73.3472}",
				"pos": "[0 54.1128 0]"
			},
			{
				"ang": "{0 0 -95.3114}",
				"pos": "[0.001 75.4194 -0.0002]"
			},
			{
				"ang": "{-8.3914 -5.5311 6.8994}",
				"pos": "[-0.001 89.4595 -0.0002]"
			},
			{
				"ang": "{14.7609 -154.7062 -45.3485}",
				"pos": "[52.25 0.002 0.0015]"
			},
			{
				"ang": "{0 0 78.5332}",
				"pos": "[0.001 80.4249 0]"
			},
			{
				"ang": "{1.6212 -13.1045 -86.2881}",
				"pos": "[0 78.0715 -0.0002]"
			},
			{
				"ang": "{11.5472 -155.8948 -8.5766}",
				"pos": "[-52.6123 0.0037 -0.0132]"
			},
			{
				"ang": "{0 0 67.6537}",
				"pos": "[0 80.4252 0]"
			},
			{
				"ang": "{2.4411 -13.144 -108.8111}",
				"pos": "[0 78.0713 -0.0002]"
			},
			{
				"ang": "{0.6611 1.0359 -22.2461}",
				"pos": "[-15.4541 199.9995 91.9375]"
			}
		],
		[
			{
				"ang": "{-0 80.2079 0.0077}",
				"pos": "[-184.2563 0 0]"
			},
			{
				"ang": "{8.2865 12.1688 101.3459}",
				"pos": "[6.4619 -24.9565 134.2558]"
			},
			{
				"ang": "{-8.0281 -3.8258 -37.329}",
				"pos": "[-0.001 27.0679 0.0005]"
			},
			{
				"ang": "{-9.0247 2.4196 -42.9565}",
				"pos": "[0 85.0154 -0.0005]"
			},
			{
				"ang": "{-3.6949 169.7552 -179.2037}",
				"pos": "[0 80.8467 18.2988]"
			},
			{
				"ang": "{-14.05 4.0624 22.2085}",
				"pos": "[0 48.6118 0]"
			},
			{
				"ang": "{4.5897 -2.8227 11.6146}",
				"pos": "[0 32.1216 -0.0001]"
			},
			{
				"ang": "{-0.6114 177.9478 6.9453}",
				"pos": "[-19.1279 15.8933 14.835]"
			},
			{
				"ang": "{-1.5283 -179.323 -173.1048}",
				"pos": "[19.126 15.8933 14.8358]"
			},
			{
				"ang": "{36.6979 -149.6121 -78.7559}",
				"pos": "[58.0732 41.0718 35.9375]"
			},
			{
				"ang": "{8.4075 -18.2388 96.5435}",
				"pos": "[-0.0005 54.1128 -0.001]"
			},
			{
				"ang": "{0 0 -116.1738}",
				"pos": "[0 75.4199 0]"
			},
			{
				"ang": "{18.4823 -5.5751 -6.1429}",
				"pos": "[0 89.4591 0.0005]"
			},
			{
				"ang": "{-31.0967 149.8297 -99.6484}",
				"pos": "[-61.498 44.4434 30.9395]"
			},
			{
				"ang": "{-9.0335 52.2274 82.3944}",
				"pos": "[0 54.1123 0]"
			},
			{
				"ang": "{0 0 -97.7254}",
				"pos": "[0.001 75.42 0.0001]"
			},
			{
				"ang": "{-6.8352 -6.3483 0.3173}",
				"pos": "[-0.001 89.4591 0.0004]"
			},
			{
				"ang": "{15.0118 -154.2607 -42.3591}",
				"pos": "[52.249 0.0017 0.0015]"
			},
			{
				"ang": "{0 0 88.9519}",
				"pos": "[0 80.425 0.001]"
			},
			{
				"ang": "{-1.8677 -13.5171 -97.6809}",
				"pos": "[0 78.0713 0.0002]"
			},
			{
				"ang": "{9.1736 -160.6631 -9.1957}",
				"pos": "[-52.6143 0.0039 -0.0132]"
			},
			{
				"ang": "{0 0 77.7963}",
				"pos": "[0 80.4255 0]"
			},
			{
				"ang": "{8.6062 -7.0806 -114.011}",
				"pos": "[0 78.0718 0.0001]"
			},
			{
				"ang": "{0.6611 1.0359 -22.2461}",
				"pos": "[-15.4531 199.9995 91.9375]"
			}
		],
		[
			{
				"ang": "{-0 83.1699 0.0186}",
				"pos": "[-192.2158 0 0]"
			},
			{
				"ang": "{6.6273 11.5148 101.8064}",
				"pos": "[12.8281 -26.9194 133.3918]"
			},
			{
				"ang": "{-7.974 -6.2183 -37.5312}",
				"pos": "[-0.001 27.0676 -0.0005]"
			},
			{
				"ang": "{-6.9683 2.0691 -42.4997}",
				"pos": "[0 85.0155 0.0005]"
			},
			{
				"ang": "{-2.4323 168.6372 -179.5339}",
				"pos": "[0 80.8467 18.2991]"
			},
			{
				"ang": "{-14.9752 3.6192 21.4062}",
				"pos": "[-0.001 48.6121 0]"
			},
			{
				"ang": "{3.2659 -3.3822 11.6572}",
				"pos": "[-0.001 32.1208 0]"
			},
			{
				"ang": "{-0.4703 178.0628 7.0231}",
				"pos": "[-19.127 15.8931 14.8352]"
			},
			{
				"ang": "{-1.3911 -179.2106 -173.0215}",
				"pos": "[19.127 15.8933 14.8358]"
			},
			{
				"ang": "{37.7178 -149.7724 -81.5128}",
				"pos": "[57.5107 41.6602 36.3701]"
			},
			{
				"ang": "{9.8526 -22.6176 94.7512}",
				"pos": "[-0.0005 54.113 -0.001]"
			},
			{
				"ang": "{0 0 -113.3475}",
				"pos": "[0 75.4209 -0.0001]"
			},
			{
				"ang": "{19.4396 -4.2434 -7.338}",
				"pos": "[0 89.4592 0.001]"
			},
			{
				"ang": "{-30.4029 149.7161 -97.3065}",
				"pos": "[-62.0342 44.2056 31.27]"
			},
			{
				"ang": "{-10.1887 49.6871 87.8634}",
				"pos": "[0 54.1143 -0.0002]"
			},
			{
				"ang": "{-0 0 -93.4657}",
				"pos": "[0 75.4199 0.0001]"
			},
			{
				"ang": "{-10.7089 -4.2249 -6.2208}",
				"pos": "[0 89.4591 -0.0001]"
			},
			{
				"ang": "{16.417 -157.1841 -38.0139}",
				"pos": "[52.248 0.0015 0.0015]"
			},
			{
				"ang": "{0 0 91.1504}",
				"pos": "[0 80.4258 -0.0005]"
			},
			{
				"ang": "{-2.6422 -11.6948 -103.8989}",
				"pos": "[0 78.0718 -0.0005]"
			},
			{
				"ang": "{9.7207 -165.0687 -8.8081}",
				"pos": "[-52.6143 0.0034 -0.0132]"
			},
			{
				"ang": "{-0 0 82.6149}",
				"pos": "[0 80.4255 0.0005]"
			},
			{
				"ang": "{10.1363 -4.2497 -114.7434}",
				"pos": "[-0.001 78.0718 0]"
			},
			{
				"ang": "{0.6611 1.0359 -22.2461}",
				"pos": "[-15.4531 200 91.9375]"
			}
		],
		[
			{
				"ang": "{-0 85.7224 0}",
				"pos": "[-200.2158 0 0]"
			},
			{
				"ang": "{4.9745 10.2984 102.072}",
				"pos": "[18.6504 -29.0601 133.8372]"
			},
			{
				"ang": "{-7.4725 -7.508 -37.4814}",
				"pos": "[-0.001 27.0679 0]"
			},
			{
				"ang": "{-5.0526 1.8123 -41.7027}",
				"pos": "[0 85.0153 0]"
			},
			{
				"ang": "{-1.4466 169.2218 -179.4705}",
				"pos": "[-0.001 80.8472 18.2991]"
			},
			{
				"ang": "{-15.1855 4.2783 21.6639}",
				"pos": "[-0.001 48.6113 0]"
			},
			{
				"ang": "{1.8993 -3.9039 11.4331}",
				"pos": "[0 32.1216 0.0001]"
			},
			{
				"ang": "{-0.3311 178.1888 7.0893}",
				"pos": "[-19.1279 15.8936 14.8352]"
			},
			{
				"ang": "{-1.2542 -179.0855 -172.9497}",
				"pos": "[19.127 15.894 14.8359]"
			},
			{
				"ang": "{38.5382 -150.0551 -85.0987}",
				"pos": "[57.1875 42.5703 36.696]"
			},
			{
				"ang": "{11.2007 -28.1037 89.5391}",
				"pos": "[0.0005 54.1125 0.001]"
			},
			{
				"ang": "{0 0 -107.3855}",
				"pos": "[0 75.4199 -0.0001]"
			},
			{
				"ang": "{21.0926 -2.9432 -7.3177}",
				"pos": "[-0.0005 89.459 0]"
			},
			{
				"ang": "{-29.9445 149.6684 -95.0805}",
				"pos": "[-62.5117 44.1641 31.7058]"
			},
			{
				"ang": "{-9.2151 46.1308 91.6151}",
				"pos": "[-0.001 54.1123 0]"
			},
			{
				"ang": "{0 0 -86.9146}",
				"pos": "[0 75.4199 -0]"
			},
			{
				"ang": "{-16.5325 -0.4397 -11.8541}",
				"pos": "[0 89.459 -0.0001]"
			},
			{
				"ang": "{17.6324 -160.7211 -33.367}",
				"pos": "[52.249 0.0017 0.002]"
			},
			{
				"ang": "{0 0 91.1036}",
				"pos": "[0 80.4255 0]"
			},
			{
				"ang": "{-2.3002 -9.7812 -108.7951}",
				"pos": "[0 78.0723 -0.0002]"
			},
			{
				"ang": "{11.0016 -168.7901 -8.3861}",
				"pos": "[-52.6133 0.0037 -0.0127]"
			},
			{
				"ang": "{0 0 86.8492}",
				"pos": "[0.001 80.4255 0.0005]"
			},
			{
				"ang": "{8.8896 -2.1389 -112.7168}",
				"pos": "[-0.001 78.0718 0.0002]"
			},
			{
				"ang": "{0.6611 1.0359 -22.2461}",
				"pos": "[-15.4521 200 91.9375]"
			}
		],
		[
			{
				"ang": "{-0 87.6361 0}",
				"pos": "[-207.9619 0 0]"
			},
			{
				"ang": "{4.3006 8.5179 101.8856}",
				"pos": "[23.1006 -31.1245 135.765]"
			},
			{
				"ang": "{-6.4577 -7.5142 -36.9914}",
				"pos": "[0 27.0675 -0.001]"
			},
			{
				"ang": "{-3.376 1.6752 -40.6171}",
				"pos": "[0 85.0151 -0.0005]"
			},
			{
				"ang": "{-0.5777 170.5659 -179.1087}",
				"pos": "[0 80.8467 18.2993]"
			},
			{
				"ang": "{-14.8582 4.9201 22.8725}",
				"pos": "[0.001 48.6113 0.0002]"
			},
			{
				"ang": "{0.5478 -4.3928 11.0445}",
				"pos": "[0 32.1211 0]"
			},
			{
				"ang": "{-0.2021 178.3126 7.1366}",
				"pos": "[-19.127 15.8936 14.8352]"
			},
			{
				"ang": "{-1.1269 -178.9617 -172.8961}",
				"pos": "[19.127 15.894 14.8358]"
			},
			{
				"ang": "{38.8549 -150.379 -88.8364}",
				"pos": "[57.1494 43.8438 36.9231]"
			},
			{
				"ang": "{12.3085 -32.9666 82.6405}",
				"pos": "[0 54.1129 0]"
			},
			{
				"ang": "{0 0 -98.8449}",
				"pos": "[0 75.4209 0.0005]"
			},
			{
				"ang": "{23.2136 -2.5383 -7.1906}",
				"pos": "[-0.0005 89.459 0]"
			},
			{
				"ang": "{-29.8146 149.6729 -93.2164}",
				"pos": "[-62.8965 44.4038 32.2769]"
			},
			{
				"ang": "{-8.4191 41.4515 92.489}",
				"pos": "[-0.0005 54.1133 0]"
			},
			{
				"ang": "{0 0 -78.5471}",
				"pos": "[-0.001 75.4199 -0.0001]"
			},
			{
				"ang": "{-20.6592 5.7308 -16.3049}",
				"pos": "[0.001 89.459 0]"
			},
			{
				"ang": "{17.905 -163.4266 -29.4422}",
				"pos": "[52.249 0.0017 0.002]"
			},
			{
				"ang": "{0 0 89.389}",
				"pos": "[0 80.4258 0.0005]"
			},
			{
				"ang": "{-1.3741 -8.4689 -111.9707}",
				"pos": "[0 78.0723 0.0005]"
			},
			{
				"ang": "{11.7761 -171.652 -9.702}",
				"pos": "[-52.6133 0.0035 -0.0137]"
			},
			{
				"ang": "{0 0 91.0227}",
				"pos": "[0 80.4255 -0.0005]"
			},
			{
				"ang": "{7.7312 -0.0858 -110.8925}",
				"pos": "[0 78.0718 -0.0002]"
			},
			{
				"ang": "{0.6611 1.0359 -22.2461}",
				"pos": "[-15.4531 200 91.9375]"
			}
		],
		[
			{
				"ang": "{-0 89.0069 0}",
				"pos": "[-215.4155 0 0]"
			},
			{
				"ang": "{3.7655 6.5054 101.2418}",
				"pos": "[26.5459 -32.8174 139.0209]"
			},
			{
				"ang": "{-5.3242 -7.2357 -36.0724}",
				"pos": "[0 27.0679 0]"
			},
			{
				"ang": "{-1.8409 1.5279 -39.1894}",
				"pos": "[0 85.0154 0]"
			},
			{
				"ang": "{0.26 172.1857 -178.6046}",
				"pos": "[0 80.8472 18.2988]"
			},
			{
				"ang": "{-14.1164 5.1745 24.6828}",
				"pos": "[0.001 48.6118 0]"
			},
			{
				"ang": "{-0.8141 -4.8216 10.9712}",
				"pos": "[-0.001 32.1216 0.0001]"
			},
			{
				"ang": "{-0.0796 178.4296 7.1703}",
				"pos": "[-19.127 15.8931 14.8352]"
			},
			{
				"ang": "{-1.0059 -178.8459 -172.8553}",
				"pos": "[19.126 15.8931 14.8356]"
			},
			{
				"ang": "{38.6168 -150.627 -92.1379}",
				"pos": "[57.2373 45.3779 37.0771]"
			},
			{
				"ang": "{12.9963 -36.9445 75.8451}",
				"pos": "[0.001 54.1126 0]"
			},
			{
				"ang": "{0 0 -88.9999}",
				"pos": "[-0.0005 75.4199 0.0005]"
			},
			{
				"ang": "{25.3548 -3.2743 -7.5722}",
				"pos": "[0.001 89.459 0.0005]"
			},
			{
				"ang": "{-29.9259 149.702 -91.6146}",
				"pos": "[-63.2803 44.8389 32.9551]"
			},
			{
				"ang": "{-8.186 36.5674 92.2002}",
				"pos": "[-0.0005 54.1123 -0.0004]"
			},
			{
				"ang": "{0 0 -71.0813}",
				"pos": "[0.001 75.4194 0]"
			},
			{
				"ang": "{-22.5002 11.9587 -18.8761}",
				"pos": "[-0.001 89.459 0]"
			},
			{
				"ang": "{17.2922 -166.0626 -25.6707}",
				"pos": "[52.249 0.0017 0.001]"
			},
			{
				"ang": "{-0 0 85.725}",
				"pos": "[-0.001 80.4258 0.0005]"
			},
			{
				"ang": "{-0.032 -7.8087 -113.5707}",
				"pos": "[0 78.0723 0.0002]"
			},
			{
				"ang": "{11.6397 -175.4554 -14.1148}",
				"pos": "[-52.6133 0.0035 -0.0146]"
			},
			{
				"ang": "{-0 0 95.9646}",
				"pos": "[0 80.4258 -0.0005]"
			},
			{
				"ang": "{8.243 1.6784 -110.3241}",
				"pos": "[0 78.0718 -0.0002]"
			},
			{
				"ang": "{0.6611 1.0359 -22.2461}",
				"pos": "[-15.4531 200 91.9375]"
			}
		],
		[
			{
				"ang": "{-0 89.8212 0.0158}",
				"pos": "[-222.8687 0 0]"
			},
			{
				"ang": "{3.2265 4.3443 99.9513}",
				"pos": "[28.6758 -34.1694 143.4396]"
			},
			{
				"ang": "{-4.0902 -6.8352 -34.7245}",
				"pos": "[0 27.0679 0.0005]"
			},
			{
				"ang": "{-0.3526 1.3421 -37.4799}",
				"pos": "[0 85.0156 0]"
			},
			{
				"ang": "{1.0253 174.0178 -177.8984}",
				"pos": "[0 80.8472 18.2988]"
			},
			{
				"ang": "{-13.0016 5.1629 26.7676}",
				"pos": "[0 48.6118 0]"
			},
			{
				"ang": "{-2.1469 -5.1281 11.1717}",
				"pos": "[0 32.1206 0.0001]"
			},
			{
				"ang": "{0.0315 178.54 7.193}",
				"pos": "[-19.1279 15.8931 14.8352]"
			},
			{
				"ang": "{-0.8947 -178.7363 -172.8268}",
				"pos": "[19.1279 15.8926 14.8359]"
			},
			{
				"ang": "{37.8039 -150.7027 -94.4437}",
				"pos": "[57.4141 47.1221 37.1401]"
			},
			{
				"ang": "{13.0726 -40.1085 70.2347}",
				"pos": "[0 54.1129 -0.001]"
			},
			{
				"ang": "{0 0 -79.2428}",
				"pos": "[-0.0005 75.4199 -0.0005]"
			},
			{
				"ang": "{26.9887 -4.9362 -8.4328}",
				"pos": "[-0.0005 89.459 -0.0005]"
			},
			{
				"ang": "{-30.2242 149.7408 -90.2221}",
				"pos": "[-63.6816 45.4507 33.6958]"
			},
			{
				"ang": "{-8.1376 31.8541 93.9373}",
				"pos": "[-0.001 54.1123 0.0005]"
			},
			{
				"ang": "{-0 0 -69.1909}",
				"pos": "[0.001 75.4197 -0.0002]"
			},
			{
				"ang": "{-22.9761 16.5503 -18.3849}",
				"pos": "[0 89.4592 -0.0005]"
			},
			{
				"ang": "{16.3366 -168.3067 -22.2216}",
				"pos": "[52.25 0.0017 0.0024]"
			},
			{
				"ang": "{-0 0 80.1819}",
				"pos": "[0.001 80.4255 0]"
			},
			{
				"ang": "{0.8929 -7.3724 -113.405}",
				"pos": "[0 78.0713 0]"
			},
			{
				"ang": "{9.2681 179.7238 -20.7506}",
				"pos": "[-52.6133 0.0037 -0.0127]"
			},
			{
				"ang": "{-0 0 97.8143}",
				"pos": "[0.001 80.4253 -0.0005]"
			},
			{
				"ang": "{9.8186 2.6711 -106.5033}",
				"pos": "[-0.001 78.0723 -0.0002]"
			},
			{
				"ang": "{0.6611 1.0359 -22.2461}",
				"pos": "[-15.4541 200 91.9375]"
			}
		],
		[
			{
				"ang": "{-0 90.0055 0}",
				"pos": "[-229.7388 0 0]"
			},
			{
				"ang": "{2.5687 1.6584 97.6949}",
				"pos": "[29.9697 -35.2061 147.865]"
			},
			{
				"ang": "{-2.6591 -6.404 -32.7726}",
				"pos": "[0 27.0677 0]"
			},
			{
				"ang": "{1.2339 1.0198 -35.4282}",
				"pos": "[0 85.0156 -0.0005]"
			},
			{
				"ang": "{1.6584 175.9611 -176.8737}",
				"pos": "[0 80.8467 18.2988]"
			},
			{
				"ang": "{-11.4864 4.5977 29.3389}",
				"pos": "[0.001 48.6118 0]"
			},
			{
				"ang": "{-3.4702 -5.1744 11.3241}",
				"pos": "[-0.002 32.1211 0]"
			},
			{
				"ang": "{0.1258 178.6391 7.2053}",
				"pos": "[-19.1279 15.8926 14.835]"
			},
			{
				"ang": "{-0.8022 -178.6372 -172.8109}",
				"pos": "[19.127 15.8926 14.8357]"
			},
			{
				"ang": "{36.4357 -150.5607 -95.214}",
				"pos": "[57.6621 49.1309 37.1147]"
			},
			{
				"ang": "{12.5036 -42.9861 65.3842}",
				"pos": "[0.0005 54.1127 0.001]"
			},
			{
				"ang": "{0 0 -70.603}",
				"pos": "[0.001 75.4194 0.001]"
			},
			{
				"ang": "{27.543 -6.2806 -8.992}",
				"pos": "[-0.0005 89.46 0]"
			},
			{
				"ang": "{-30.7012 149.7859 -89.0664}",
				"pos": "[-64.1191 46.3213 34.4785]"
			},
			{
				"ang": "{-8.2333 28.3289 95.5892}",
				"pos": "[0 54.1123 0]"
			},
			{
				"ang": "{0 0 -70.3878}",
				"pos": "[0 75.4199 0]"
			},
			{
				"ang": "{-23.2432 18.8135 -15.5268}",
				"pos": "[0 89.4592 0]"
			},
			{
				"ang": "{15.8324 -170.1143 -20.237}",
				"pos": "[52.249 0.0016 0.002]"
			},
			{
				"ang": "{0 0 73.9271}",
				"pos": "[-0.001 80.4253 -0.0005]"
			},
			{
				"ang": "{0.309 -6.1529 -111.7012}",
				"pos": "[0 78.0718 -0.0005]"
			},
			{
				"ang": "{2.988 174.1723 -29.4196}",
				"pos": "[-52.6123 0.0035 -0.0137]"
			},
			{
				"ang": "{0 0 97.152}",
				"pos": "[0.002 80.4253 0]"
			},
			{
				"ang": "{12.519 2.8159 -99.5486}",
				"pos": "[-0.001 78.0723 0.0005]"
			},
			{
				"ang": "{0.6611 1.0359 -22.2461}",
				"pos": "[-15.4531 200 91.9375]"
			}
		],
		[
			{
				"ang": "{-0 90.0055 0}",
				"pos": "[-237.292 0 0]"
			},
			{
				"ang": "{1.6236 -1.4645 95.094}",
				"pos": "[30.4912 -36.7271 151.2742]"
			},
			{
				"ang": "{-1.2009 -5.996 -30.692}",
				"pos": "[0 27.0678 -0.0005]"
			},
			{
				"ang": "{2.8184 0.6228 -33.307}",
				"pos": "[0.001 85.0154 -0.0005]"
			},
			{
				"ang": "{2.1656 178.0291 -175.7082}",
				"pos": "[0 80.8462 18.2988]"
			},
			{
				"ang": "{-9.6161 3.6948 32.0992}",
				"pos": "[0 48.6123 0.0002]"
			},
			{
				"ang": "{-4.7353 -4.836 11.25}",
				"pos": "[-0.001 32.1211 0]"
			},
			{
				"ang": "{0.2016 178.7387 7.2097}",
				"pos": "[-19.127 15.8936 14.835]"
			},
			{
				"ang": "{-0.7271 -178.5389 -172.8023}",
				"pos": "[19.127 15.8936 14.8357]"
			},
			{
				"ang": "{34.8445 -150.3298 -95.007}",
				"pos": "[57.9629 51.231 36.9526]"
			},
			{
				"ang": "{11.445 -45.5796 60.8976}",
				"pos": "[0.001 54.1125 -0.001]"
			},
			{
				"ang": "{0 0 -63.216}",
				"pos": "[-0.0005 75.4199 -0.001]"
			},
			{
				"ang": "{27.4227 -7.1095 -9.5623}",
				"pos": "[0.0005 89.459 0]"
			},
			{
				"ang": "{-31.2887 149.8251 -88.097}",
				"pos": "[-64.5645 47.2925 35.2573]"
			},
			{
				"ang": "{-8.3013 26.1105 96.4494}",
				"pos": "[0.0005 54.1133 -0.0001]"
			},
			{
				"ang": "{0 0 -72.6065}",
				"pos": "[0.001 75.4197 0.0005]"
			},
			{
				"ang": "{-23.8892 19.3736 -11.6613}",
				"pos": "[-0.001 89.459 0.0005]"
			},
			{
				"ang": "{15.4842 -171.5798 -19.0572}",
				"pos": "[52.249 0.0016 0.001]"
			},
			{
				"ang": "{0 0 68.1072}",
				"pos": "[0 80.4254 0.001]"
			},
			{
				"ang": "{-1.3769 -4.8258 -109.7654}",
				"pos": "[-0.001 78.072 0.0005]"
			},
			{
				"ang": "{-4.4609 169.6773 -38.1119}",
				"pos": "[-52.6133 0.0036 -0.0132]"
			},
			{
				"ang": "{0 0 95.2346}",
				"pos": "[0.001 80.4258 0.0005]"
			},
			{
				"ang": "{14.4854 3.7959 -92.2034}",
				"pos": "[-0.001 78.0718 0.0005]"
			},
			{
				"ang": "{0.6611 1.0359 -22.2461}",
				"pos": "[-15.4531 200 91.9375]"
			}
		],
		[
			{
				"ang": "{-0 90.0055 0}",
				"pos": "[-247.646 0 0]"
			},
			{
				"ang": "{0.396 -5.1004 92.7427}",
				"pos": "[30.3545 -40.2642 153.533]"
			},
			{
				"ang": "{0.1328 -5.6454 -29.0168}",
				"pos": "[0.001 27.0678 0]"
			},
			{
				"ang": "{4.2826 0.1962 -31.372}",
				"pos": "[0.001 85.0159 0.0005]"
			},
			{
				"ang": "{2.6852 -179.5394 -174.6513}",
				"pos": "[-0.001 80.8467 18.2993]"
			},
			{
				"ang": "{-7.0237 2.2283 34.8852}",
				"pos": "[0 48.6123 0]"
			},
			{
				"ang": "{-5.8972 -3.7124 10.9382}",
				"pos": "[0 32.1206 0]"
			},
			{
				"ang": "{0.2565 178.8395 7.2079}",
				"pos": "[-19.1279 15.8936 14.835]"
			},
			{
				"ang": "{-0.6718 -178.4368 -172.8032}",
				"pos": "[19.127 15.8926 14.8357]"
			},
			{
				"ang": "{33.21 -150.0877 -94.1123}",
				"pos": "[58.2949 53.2373 36.6392]"
			},
			{
				"ang": "{10.0974 -48.0088 57.3815}",
				"pos": "[0.0005 54.1122 0]"
			},
			{
				"ang": "{0 0 -58.2916}",
				"pos": "[0 75.4194 0]"
			},
			{
				"ang": "{26.3782 -6.5756 -9.1537}",
				"pos": "[-0.0005 89.4585 0]"
			},
			{
				"ang": "{-31.9534 149.8584 -87.309}",
				"pos": "[-65.0039 48.209 35.9902]"
			},
			{
				"ang": "{-8.3623 25.34 95.8182}",
				"pos": "[0.0005 54.1123 -0.0004]"
			},
			{
				"ang": "{0 0 -74.2146}",
				"pos": "[0 75.4202 -0.0005]"
			},
			{
				"ang": "{-24.7776 18.5542 -8.1341}",
				"pos": "[0 89.4595 0]"
			},
			{
				"ang": "{14.0195 -172.878 -18.015}",
				"pos": "[52.249 0.0017 0.0015]"
			},
			{
				"ang": "{0 0 62.9428}",
				"pos": "[0 80.4256 0]"
			},
			{
				"ang": "{-3.0675 -4.2063 -108.1134}",
				"pos": "[0.001 78.0715 0.0005]"
			},
			{
				"ang": "{-11.9126 165.942 -45.4418}",
				"pos": "[-52.6123 0.0036 -0.0132]"
			},
			{
				"ang": "{0 0 91.4312}",
				"pos": "[0.0005 80.4253 0]"
			},
			{
				"ang": "{15.4201 6.2949 -84.4917}",
				"pos": "[-0.0005 78.0718 0.0005]"
			},
			{
				"ang": "{0.6611 1.0359 -22.2461}",
				"pos": "[-15.4531 200 91.9375]"
			}
		],
		[
			{
				"ang": "{-0 90.0055 0}",
				"pos": "[-257.6162 0 0]"
			},
			{
				"ang": "{-1.0379 -8.7677 91.0145}",
				"pos": "[29.3047 -43.2217 154.6204]"
			},
			{
				"ang": "{1.2982 -5.4256 -28.0492}",
				"pos": "[-0.001 27.0678 0.0005]"
			},
			{
				"ang": "{5.6073 -0.2734 -29.911}",
				"pos": "[-0.001 85.0154 0]"
			},
			{
				"ang": "{3.2923 -176.5474 -173.9902}",
				"pos": "[-0.002 80.8462 18.2993]"
			},
			{
				"ang": "{-3.9759 0.5629 37.2179}",
				"pos": "[-0.002 48.6118 0]"
			},
			{
				"ang": "{-6.9197 -1.7332 10.5757}",
				"pos": "[-0.001 32.1211 0.0002]"
			},
			{
				"ang": "{0.288 178.9545 7.1975}",
				"pos": "[-19.127 15.8931 14.835]"
			},
			{
				"ang": "{-0.6393 -178.3218 -172.8107}",
				"pos": "[19.126 15.8931 14.8359]"
			},
			{
				"ang": "{31.721 -149.888 -92.803}",
				"pos": "[58.6465 54.9609 36.1436]"
			},
			{
				"ang": "{8.298 -49.603 56.2522}",
				"pos": "[0 54.1125 0]"
			},
			{
				"ang": "{0 0 -57.535}",
				"pos": "[0 75.4197 0]"
			},
			{
				"ang": "{25.056 -4.8383 -7.2319}",
				"pos": "[0.0005 89.4585 -0.001]"
			},
			{
				"ang": "{-32.6625 149.8865 -86.7215}",
				"pos": "[-65.4424 48.9272 36.6094]"
			},
			{
				"ang": "{-8.5381 25.4346 93.7084}",
				"pos": "[0 54.1123 0.0001]"
			},
			{
				"ang": "{0 0 -75.7807}",
				"pos": "[0 75.4199 0.0005]"
			},
			{
				"ang": "{-25.701 16.7209 -4.6226}",
				"pos": "[0 89.46 0.0002]"
			},
			{
				"ang": "{11.0813 -173.7492 -16.6946}",
				"pos": "[52.249 0.0017 0.002]"
			},
			{
				"ang": "{0 0 58.4449}",
				"pos": "[-0.002 80.4254 0]"
			},
			{
				"ang": "{-4.0701 -4.7988 -106.8127}",
				"pos": "[0.001 78.0723 0]"
			},
			{
				"ang": "{-18.2655 162.5741 -50.4783}",
				"pos": "[-52.6133 0.0036 -0.0132]"
			},
			{
				"ang": "{0 0 84.7087}",
				"pos": "[0 80.4258 0]"
			},
			{
				"ang": "{14.5545 10.798 -76.0632}",
				"pos": "[-0.0005 78.0723 0]"
			},
			{
				"ang": "{0.6611 1.0359 -22.2461}",
				"pos": "[-15.4541 200 91.9375]"
			}
		],
		[
			{
				"ang": "{-0 90.0055 0}",
				"pos": "[-267.2739 0 0]"
			},
			{
				"ang": "{-2.5145 -12.4547 90.1824}",
				"pos": "[27.0938 -45.1382 154.8078]"
			},
			{
				"ang": "{2.4365 -5.3356 -27.8189}",
				"pos": "[0 27.0677 -0.0005]"
			},
			{
				"ang": "{6.9922 -0.8099 -29.143}",
				"pos": "[0 85.0156 0]"
			},
			{
				"ang": "{3.5587 -172.8299 -173.8849}",
				"pos": "[0.001 80.8472 18.2993]"
			},
			{
				"ang": "{-1.4948 -0.1522 39.0748}",
				"pos": "[0.001 48.6123 0.0002]"
			},
			{
				"ang": "{-7.7981 0.2829 10.4505}",
				"pos": "[0.001 32.1211 0]"
			},
			{
				"ang": "{0.3045 179.0671 7.183}",
				"pos": "[-19.1279 15.8931 14.835]"
			},
			{
				"ang": "{-0.6216 -178.2092 -172.8239}",
				"pos": "[19.1279 15.8931 14.8359]"
			},
			{
				"ang": "{30.4599 -149.7577 -91.4016}",
				"pos": "[59.0059 56.2959 35.4277]"
			},
			{
				"ang": "{6.0047 -50.0877 57.7781}",
				"pos": "[0.0005 54.1127 -0.001]"
			},
			{
				"ang": "{0 0 -60.6911}",
				"pos": "[0.0005 75.4199 0]"
			},
			{
				"ang": "{23.9171 -2.6556 -4.1254}",
				"pos": "[-0.0005 89.459 0.001]"
			},
			{
				"ang": "{-33.3732 149.9111 -86.2947}",
				"pos": "[-65.8623 49.3481 37.0605]"
			},
			{
				"ang": "{-8.9435 25.9549 90.0086}",
				"pos": "[0 54.1133 -0.0001]"
			},
			{
				"ang": "{0 0 -77.1201}",
				"pos": "[0 75.4197 -0.0005]"
			},
			{
				"ang": "{-26.2327 14.5888 -1.0959}",
				"pos": "[0 89.4595 -0.0005]"
			},
			{
				"ang": "{7.7076 -173.7626 -14.6599}",
				"pos": "[52.249 0.0016 0.001]"
			},
			{
				"ang": "{0 0 54.4147}",
				"pos": "[0 80.4256 0]"
			},
			{
				"ang": "{-5.2174 -6.0581 -105.78}",
				"pos": "[-0.001 78.0723 -0.0004]"
			},
			{
				"ang": "{-23.5426 159.5293 -52.395}",
				"pos": "[-52.6133 0.0035 -0.0132]"
			},
			{
				"ang": "{0 0 75.3086}",
				"pos": "[0.001 80.4258 0]"
			},
			{
				"ang": "{11.3252 15.5443 -68.0088}",
				"pos": "[-0.001 78.0717 0.001]"
			},
			{
				"ang": "{0.6611 1.0359 -22.2461}",
				"pos": "[-15.4541 200 91.9375]"
			}
		],
		[
			{
				"ang": "{-0 90.0055 0}",
				"pos": "[-276.4873 0 0]"
			},
			{
				"ang": "{-3.9498 -16.7023 90.6176}",
				"pos": "[23.8301 -44.9053 154.1157]"
			},
			{
				"ang": "{3.7008 -5.169 -28.3836}",
				"pos": "[0.001 27.0677 0]"
			},
			{
				"ang": "{8.6074 -1.3362 -29.3771}",
				"pos": "[0 85.0154 -0.0005]"
			},
			{
				"ang": "{3.4838 -169.2695 -174.5337}",
				"pos": "[0 80.8467 18.2988]"
			},
			{
				"ang": "{0.2772 0.0638 40.4216}",
				"pos": "[0 48.6123 0.0002]"
			},
			{
				"ang": "{-8.4937 1.6156 10.6906}",
				"pos": "[-0.001 32.1211 0]"
			},
			{
				"ang": "{0.3033 179.1489 7.1691}",
				"pos": "[-19.1279 15.894 14.835]"
			},
			{
				"ang": "{-0.6229 -178.1254 -172.8376}",
				"pos": "[19.127 15.8936 14.8354]"
			},
			{
				"ang": "{29.4679 -149.6856 -89.9628}",
				"pos": "[59.3721 57.0757 34.4287]"
			},
			{
				"ang": "{3.3073 -49.6657 61.1226}",
				"pos": "[0 54.1123 0]"
			},
			{
				"ang": "{0 0 -66.4889}",
				"pos": "[0 75.4204 -0.001]"
			},
			{
				"ang": "{22.9294 -0.708 -0.7028}",
				"pos": "[0.0005 89.46 -0.001]"
			},
			{
				"ang": "{-34.05 149.9354 -86.036}",
				"pos": "[-66.249 49.3379 37.2539]"
			},
			{
				"ang": "{-9.395 26.5365 85.0511}",
				"pos": "[0 54.1113 -0.0004]"
			},
			{
				"ang": "{0 0 -77.8636}",
				"pos": "[-0.001 75.42 0]"
			},
			{
				"ang": "{-26.4139 12.8833 1.908}",
				"pos": "[0 89.4595 -0.0002]"
			},
			{
				"ang": "{3.629 -172.7979 -11.4371}",
				"pos": "[52.249 0.0016 0.0015]"
			},
			{
				"ang": "{0 0 50.5783}",
				"pos": "[0.002 80.4253 -0.0005]"
			},
			{
				"ang": "{-6.8059 -7.9339 -105.0215}",
				"pos": "[-0.001 78.0718 -0.0001]"
			},
			{
				"ang": "{-28.0216 156.0897 -50.0896}",
				"pos": "[-52.6133 0.0034 -0.0137]"
			},
			{
				"ang": "{0 0 64.1117}",
				"pos": "[-0.0005 80.4248 -0.0002]"
			},
			{
				"ang": "{6.181 18.9529 -61.8702}",
				"pos": "[0.001 78.072 0]"
			},
			{
				"ang": "{0.6611 1.0359 -22.2461}",
				"pos": "[-15.4541 200 91.9375]"
			}
		],
		[
			{
				"ang": "{-0 90.0055 0}",
				"pos": "[-285.0737 0 0]"
			},
			{
				"ang": "{-5.7859 -22.6884 93.393}",
				"pos": "[19.9385 -40.9995 152.3603]"
			},
			{
				"ang": "{5.4544 -4.6187 -30.1344}",
				"pos": "[0 27.0679 -0.0005]"
			},
			{
				"ang": "{11.0791 -1.7089 -31.1993}",
				"pos": "[0 85.0156 -0.0002]"
			},
			{
				"ang": "{4.5511 -169.6646 -176.1058}",
				"pos": "[-0.001 80.8467 18.2993]"
			},
			{
				"ang": "{3.6396 -1.8697 40.3754}",
				"pos": "[0 48.6123 -0.0002]"
			},
			{
				"ang": "{-8.4325 2.0112 11.2047}",
				"pos": "[0 32.1211 0]"
			},
			{
				"ang": "{0.3137 179.1463 7.1699}",
				"pos": "[-19.1279 15.8931 14.835]"
			},
			{
				"ang": "{-0.6123 -178.1289 -172.8369}",
				"pos": "[19.127 15.8931 14.8359]"
			},
			{
				"ang": "{28.7801 -149.6575 -88.5898}",
				"pos": "[59.7852 56.8584 32.8652]"
			},
			{
				"ang": "{0.2641 -48.3238 64.9962}",
				"pos": "[0.0005 54.1122 -0.001]"
			},
			{
				"ang": "{0 0 -73.0727}",
				"pos": "[0 75.4194 0.001]"
			},
			{
				"ang": "{22.7162 -0.3897 1.6233}",
				"pos": "[0 89.4595 0]"
			},
			{
				"ang": "{-34.6474 149.9574 -85.9474}",
				"pos": "[-66.5244 48.5171 36.8772]"
			},
			{
				"ang": "{-9.6461 26.5216 80.7511}",
				"pos": "[-0.0005 54.1133 -0.0004]"
			},
			{
				"ang": "{0 0 -79.9429}",
				"pos": "[-0.001 75.4198 0]"
			},
			{
				"ang": "{-26.3854 11.354 4.169}",
				"pos": "[0 89.4585 -0.0002]"
			},
			{
				"ang": "{-2.3422 -171.4697 -5.7826}",
				"pos": "[52.249 0.0016 0.0012]"
			},
			{
				"ang": "{0 0 45.5761}",
				"pos": "[0 80.4255 0.0005]"
			},
			{
				"ang": "{-8.8988 -10.5447 -103.8636}",
				"pos": "[0 78.0723 0]"
			},
			{
				"ang": "{-31.1963 149.8696 -40.4516}",
				"pos": "[-52.6133 0.0037 -0.0132]"
			},
			{
				"ang": "{0 0 51.2835}",
				"pos": "[0 80.4258 -0.0005]"
			},
			{
				"ang": "{-0.4154 20.5744 -58.6234}",
				"pos": "[0.0005 78.0723 0]"
			},
			{
				"ang": "{0.6611 1.0359 -22.2461}",
				"pos": "[-15.4541 200 91.9375]"
			}
		],
		[
			{
				"ang": "{-0 90.0055 0}",
				"pos": "[-293.2891 0 0]"
			},
			{
				"ang": "{-7.2442 -28.2443 97.2556}",
				"pos": "[15.2715 -35.0215 149.3668]"
			},
			{
				"ang": "{7.1469 -3.3113 -32.2028}",
				"pos": "[0 27.068 0]"
			},
			{
				"ang": "{13.0717 -2.0788 -33.7736}",
				"pos": "[0.001 85.0156 -0.0005]"
			},
			{
				"ang": "{5.8322 -172.4444 -178.3689}",
				"pos": "[0 80.8462 18.2993]"
			},
			{
				"ang": "{8.0597 -4.955 38.8883}",
				"pos": "[0 48.6123 0]"
			},
			{
				"ang": "{-7.7957 2.0631 11.8481}",
				"pos": "[0 32.1211 -0.0002]"
			},
			{
				"ang": "{0.3323 179.09 7.1803}",
				"pos": "[-19.127 15.8926 14.8354]"
			},
			{
				"ang": "{-0.5951 -178.1863 -172.8248}",
				"pos": "[19.127 15.8926 14.8359]"
			},
			{
				"ang": "{28.3322 -149.6591 -87.3915}",
				"pos": "[60.373 56.1216 31.0315]"
			},
			{
				"ang": "{-3.0923 -46.0426 68.0835}",
				"pos": "[0.0005 54.1118 0]"
			},
			{
				"ang": "{0 0 -78.3876}",
				"pos": "[0.001 75.4199 0]"
			},
			{
				"ang": "{23.8351 -2.3213 2.3943}",
				"pos": "[-0.001 89.4595 -0.001]"
			},
			{
				"ang": "{-35.1426 149.9797 -86.0029}",
				"pos": "[-66.5547 47.3555 36.1694]"
			},
			{
				"ang": "{-9.6406 25.6958 77.6452}",
				"pos": "[-0.0005 54.1143 0.0005]"
			},
			{
				"ang": "{-0 0 -84.1573}",
				"pos": "[-0.001 75.4198 0.0005]"
			},
			{
				"ang": "{-26.5847 9.5089 6.9317}",
				"pos": "[-0.001 89.459 0.0002]"
			},
			{
				"ang": "{-7.8723 -169.4208 1.2392}",
				"pos": "[52.249 0.0018 0.0015]"
			},
			{
				"ang": "{-0 0 39.9201}",
				"pos": "[-0.001 80.4258 -0.0002]"
			},
			{
				"ang": "{-11.6714 -13.772 -102.6558}",
				"pos": "[0 78.0718 -0.0001]"
			},
			{
				"ang": "{-31.1613 143.775 -25.7159}",
				"pos": "[-52.6133 0.0037 -0.0132]"
			},
			{
				"ang": "{0 0 32.8308}",
				"pos": "[0 80.4258 0]"
			},
			{
				"ang": "{-8.8156 19.4428 -53.1966}",
				"pos": "[0.0005 78.0723 0]"
			},
			{
				"ang": "{0.6611 1.0359 -22.2461}",
				"pos": "[-15.4531 200 91.9375]"
			}
		],
		[
			{
				"ang": "{-0 90.0055 0}",
				"pos": "[-300.9624 0 0]"
			},
			{
				"ang": "{-7.4433 -30.082 100.571}",
				"pos": "[8.5186 -28.1548 141.7489]"
			},
			{
				"ang": "{7.8854 -0.7149 -33.9413}",
				"pos": "[0 27.068 0.0002]"
			},
			{
				"ang": "{12.4996 -2.3731 -36.1353}",
				"pos": "[-0.001 85.0156 -0.0005]"
			},
			{
				"ang": "{6.368 -174.7006 179.4841}",
				"pos": "[-0.001 80.8472 18.2991]"
			},
			{
				"ang": "{12.2333 -6.9786 36.3484}",
				"pos": "[-0.001 48.6123 0.0002]"
			},
			{
				"ang": "{-6.7583 2.1253 12.396}",
				"pos": "[-0.001 32.1216 -0.0001]"
			},
			{
				"ang": "{0.3378 179.0331 7.1891}",
				"pos": "[-19.127 15.8936 14.8354]"
			},
			{
				"ang": "{-0.5899 -178.2432 -172.816}",
				"pos": "[19.126 15.8936 14.8359]"
			},
			{
				"ang": "{28.1045 -149.6734 -86.4984}",
				"pos": "[61.3154 55.2715 29.2793]"
			},
			{
				"ang": "{-6.8039 -42.5307 71.2111}",
				"pos": "[0.0005 54.1121 0]"
			},
			{
				"ang": "{0 0 -84.1919}",
				"pos": "[-0.001 75.4199 -0.0005]"
			},
			{
				"ang": "{26.9723 -6.7368 2.9539}",
				"pos": "[0.0005 89.4585 0]"
			},
			{
				"ang": "{-35.4966 150.0044 -86.2095}",
				"pos": "[-66.1436 46.3091 35.5334]"
			},
			{
				"ang": "{-9.1192 23.3854 76.5757}",
				"pos": "[0 54.1133 0.0007]"
			},
			{
				"ang": "{0 0 -92.9593}",
				"pos": "[0 75.4202 0.0005]"
			},
			{
				"ang": "{-27.8566 6.5466 13.8881}",
				"pos": "[0 89.4595 -0.0004]"
			},
			{
				"ang": "{-10.3046 -164.2815 5.9116}",
				"pos": "[52.251 0.0017 0.0012]"
			},
			{
				"ang": "{0 0 41.4202}",
				"pos": "[-0.001 80.4258 -0.0002]"
			},
			{
				"ang": "{-16.9107 -17.2214 -104.1544}",
				"pos": "[-0.001 78.0723 0.0005]"
			},
			{
				"ang": "{-28.3375 141.4868 -28.8596}",
				"pos": "[-52.6123 0.0035 -0.0137]"
			},
			{
				"ang": "{0 0 41.4347}",
				"pos": "[0 80.4258 0]"
			},
			{
				"ang": "{-12.4972 18.6061 -55.3888}",
				"pos": "[0 78.0718 0]"
			},
			{
				"ang": "{0.6611 1.0359 -22.2461}",
				"pos": "[-15.4531 200 91.9375]"
			}
		]
	]
}